{
  "257850": {
    "Name": "Hyper.Light.Drifter",
    "AppID": 257850,
    "InstalledBuild": 10930509,
    "LatestDate": "2023-04-04T19:48:08.000Z",
    "Rating": 84,
    "LatestBuild": 10930509,
    "RatingPercent": 92.9694275802255,
    "ReviewsTotal": 18448,
    "ReviewsPositive": 17151,
    "ReviewsNegative": 1297,
    "ReviewSummary": "Very Positive"
  },
  "268910": {
    "Name": "Cuphead",
    "AppID": 268910,
    "InstalledBuild": 20241530,
    "LatestDate": "2025-10-03T22:10:37.000Z",
    "Rating": 88,
    "LatestBuild": 20241530,
    "RatingPercent": 96.24845082744041,
    "ReviewsTotal": 205755,
    "ReviewsPositive": 198036,
    "ReviewsNegative": 7719,
    "ReviewSummary": "Overwhelmingly Positive"
  },
  "323190": {
    "Name": "Frostpunk",
    "AppID": 323190,
    "InstalledBuild": 20303936,
    "LatestDate": "2025-10-20T09:42:34.000Z",
    "LatestBuild": 20303936,
    "RatingPercent": 92.71176701847763,
    "ReviewsTotal": 132268,
    "ReviewsPositive": 122628,
    "ReviewsNegative": 9640,
    "ReviewSummary": "Very Positive"
  },
  "330020": {
    "Name": "Children.of.Morta",
    "AppID": 330020,
    "InstalledBuild": 8334433,
    "LatestDate": "2022-03-08T16:02:23.000Z",
    "Rating": 82,
    "LatestBuild": 8334433,
    "RatingPercent": 88.53500355366027,
    "ReviewsTotal": 22512,
    "ReviewsPositive": 19931,
    "ReviewsNegative": 2581,
    "ReviewSummary": "Very Positive"
  },
  "367520": {
    "Name": "Hollow.Knight",
    "AppID": 367520,
    "InstalledBuild": 21656419,
    "LatestDate": "2026-02-05T23:18:23.000Z",
    "Status": "✅ Up-to-date",
    "Rating": 87,
    "LatestBuild": 21656419,
    "RatingPercent": 96.91675173281146,
    "ReviewsTotal": 531939,
    "ReviewsPositive": 515538,
    "ReviewsNegative": 16401,
    "ReviewSummary": "Overwhelmingly Positive"
  },
  "368340": {
    "Name": "CrossCode",
    "AppID": 368340,
    "InstalledBuild": 20004663,
    "LatestDate": "2025-09-20T13:15:00.000Z",
    "Rating": 86,
    "LatestBuild": 20004663,
    "RatingPercent": 92.85673758865248,
    "ReviewsTotal": 17625,
    "ReviewsPositive": 16366,
    "ReviewsNegative": 1259,
    "ReviewSummary": "Very Positive"
  },
  "394310": {
    "Name": "Punch.Club",
    "AppID": 394310,
    "InstalledBuild": 11412837,
    "LatestDate": "2024-01-26T08:51:08.000Z",
    "Rating": 73,
    "LatestBuild": 1734185,
    "RatingPercent": 80.5037555037555,
    "ReviewsTotal": 15444,
    "ReviewsPositive": 12433,
    "ReviewsNegative": 3011,
    "ReviewSummary": "Very Positive"
  },
  "503560": {
    "Name": "911.Operator",
    "AppID": 503560,
    "InstalledBuild": 7533741,
    "LatestDate": "2021-10-14T15:35:34.000Z",
    "Rating": 68,
    "LatestBuild": 7533741,
    "RatingPercent": 88.62633082316282,
    "ReviewsTotal": 19255,
    "ReviewsPositive": 17065,
    "ReviewsNegative": 2190,
    "ReviewSummary": "Very Positive"
  },
  "504230": {
    "Name": "Celeste",
    "AppID": 504230,
    "InstalledBuild": 17282758,
    "LatestDate": "2025-02-07T17:00:06.000Z",
    "Rating": 88,
    "LatestBuild": 17282758,
    "RatingPercent": 97.42507663030057,
    "ReviewsTotal": 137674,
    "ReviewsPositive": 134129,
    "ReviewsNegative": 3545,
    "ReviewSummary": "Overwhelmingly Positive"
  },
  "553420": {
    "Name": "Tunic",
    "AppID": 553420,
    "InstalledBuild": 10650562,
    "LatestDate": "2023-03-02T20:14:47.000Z",
    "Status": "✅ Up-to-date",
    "Rating": 85,
    "LatestBuild": 10650562,
    "RatingPercent": 91.48364485981308,
    "ReviewsTotal": 17120,
    "ReviewsPositive": 15662,
    "ReviewsNegative": 1458,
    "ReviewSummary": "Very Positive"
  },
  "588650": {
    "Name": "Dead.Cells",
    "AppID": 588650,
    "InstalledBuild": 15492902,
    "LatestDate": "2024-08-27T08:14:59.000Z",
    "Status": "✅ Up-to-date",
    "Rating": 89,
    "LatestBuild": 15492902,
    "RatingPercent": 97.04595922212502,
    "ReviewsTotal": 178332,
    "ReviewsPositive": 173064,
    "ReviewsNegative": 5268,
    "ReviewSummary": "Overwhelmingly Positive"
  },
  "632360": {
    "Name": "Risk.of.Rain.2",
    "AppID": 632360,
    "InstalledBuild": 21587608,
    "LatestDate": "2026-03-19T09:27:48.585Z",
    "RatingPercent": 93.75371473189833,
    "ReviewsTotal": 343228,
    "ReviewsPositive": 321789,
    "ReviewsNegative": 21439,
    "ReviewSummary": "Very Positive"
  },
  "632470": {
    "Name": "Disco.Elysium",
    "AppID": 632470,
    "InstalledBuild": 21464562,
    "LatestDate": "2026-01-23T14:24:58.000Z",
    "Rating": 97,
    "LatestBuild": 21464562,
    "RatingPercent": 92.71594430973295,
    "ReviewsTotal": 124546,
    "ReviewsPositive": 115474,
    "ReviewsNegative": 9072,
    "ReviewSummary": "Very Positive"
  },
  "653530": {
    "Name": "Return.of.the.Obra.Dinn",
    "AppID": 653530,
    "InstalledBuild": 9550393,
    "LatestDate": "2022-09-20T07:24:13.000Z",
    "Rating": 89,
    "LatestBuild": 9550393,
    "RatingPercent": 96.72603850659299,
    "ReviewsTotal": 33293,
    "ReviewsPositive": 32203,
    "ReviewsNegative": 1090,
    "ReviewSummary": "Overwhelmingly Positive"
  },
  "686060": {
    "Name": "Mewgenics",
    "AppID": 686060,
    "InstalledBuild": 22384947,
    "LatestDate": "2026-03-18T00:04:58.000Z",
    "LatestBuild": 22384947,
    "RatingPercent": 92.11916493117286,
    "ReviewsTotal": 39374,
    "ReviewsPositive": 36271,
    "ReviewsNegative": 3103,
    "ReviewSummary": "Very Positive"
  },
  "690830": {
    "Name": "Foundation",
    "AppID": 690830,
    "InstalledBuild": 21621209,
    "LatestDate": "2026-02-24T15:06:13.000Z",
    "Rating": 84,
    "LatestBuild": 22062501,
    "RatingPercent": 86.38886516949876,
    "ReviewsTotal": 23422,
    "ReviewsPositive": 20234,
    "ReviewsNegative": 3188,
    "ReviewSummary": "Very Positive"
  },
  "692850": {
    "Name": "Bloodstained.Ritual.of.the.Night",
    "AppID": 692850,
    "InstalledBuild": 20844919,
    "LatestDate": "2025-12-23T15:37:31.000Z",
    "Rating": 93,
    "LatestBuild": 20844919,
    "RatingPercent": 93.36206263313827,
    "ReviewsTotal": 40841,
    "ReviewsPositive": 38130,
    "ReviewsNegative": 2711,
    "ReviewSummary": "Very Positive"
  },
  "774181": {
    "Name": "Rhythm.Doctor",
    "AppID": 774181,
    "InstalledBuild": 21254178,
    "LatestDate": "2026-03-17T00:28:03.000Z",
    "Rating": 87,
    "LatestBuild": 22372042,
    "RatingPercent": 98.22581900241227,
    "ReviewsTotal": 25702,
    "ReviewsPositive": 25246,
    "ReviewsNegative": 456,
    "ReviewSummary": "Overwhelmingly Positive"
  },
  "774361": {
    "Name": "Blasphemous",
    "AppID": 774361,
    "InstalledBuild": 20206233,
    "LatestDate": "2025-10-03T09:46:58.000Z",
    "Status": "✅ Up-to-date",
    "Rating": 77,
    "LatestBuild": 20206233,
    "RatingPercent": 89.82649970030295,
    "ReviewsTotal": 61729,
    "ReviewsPositive": 55449,
    "ReviewsNegative": 6280,
    "ReviewSummary": "Very Positive"
  },
  "867210": {
    "Name": "Songs.of.Conquest",
    "AppID": 867210,
    "InstalledBuild": 22401468,
    "LatestDate": "2026-03-18T18:46:13.000Z",
    "Rating": 85,
    "LatestBuild": 22401468,
    "RatingPercent": 85.75359217364719,
    "ReviewsTotal": 13084,
    "ReviewsPositive": 11220,
    "ReviewsNegative": 1864,
    "ReviewSummary": "Very Positive"
  },
  "894020": {
    "Name": "Deaths.Door",
    "AppID": 894020,
    "InstalledBuild": 7480208,
    "LatestDate": "2021-10-05T10:21:41.000Z",
    "Rating": 85,
    "LatestBuild": 7480208,
    "RatingPercent": 93.20328150338644,
    "ReviewsTotal": 20966,
    "ReviewsPositive": 19541,
    "ReviewsNegative": 1425,
    "ReviewSummary": "Very Positive"
  },
  "921570": {
    "Name": "Octopath.Traveler",
    "AppID": 921570,
    "InstalledBuild": 5272616,
    "LatestDate": "2020-07-22T16:55:34.000Z",
    "Rating": 80,
    "RatingPercent": 85.81673306772907,
    "ReviewsTotal": 16315,
    "ReviewsPositive": 14001,
    "ReviewsNegative": 2314,
    "ReviewSummary": "Very Positive",
    "LatestBuild": 5272616
  },
  "1030300": {
    "Name": "Hollow.Knight.Silksong",
    "AppID": 1030300,
    "InstalledBuild": 22372218,
    "LatestDate": "2026-03-17T03:35:38.000Z",
    "Status": "✅ Up-to-date",
    "Rating": 90,
    "LatestBuild": 22372218,
    "RatingPercent": 89.07824171735027,
    "ReviewsTotal": 397729,
    "ReviewsPositive": 354290,
    "ReviewsNegative": 43439,
    "ReviewSummary": "Very Positive"
  },
  "1161590": {
    "Name": "Punch.Club.2.Fast.Forward",
    "AppID": 1161590,
    "InstalledBuild": 20464979,
    "LatestDate": "2025-10-20T14:12:49.000Z",
    "Status": "✅ Up-to-date",
    "Rating": 82,
    "LatestBuild": 20464979,
    "RatingPercent": 82.54189944134079,
    "ReviewsTotal": 4296,
    "ReviewsPositive": 3546,
    "ReviewsNegative": 750,
    "ReviewSummary": "Very Positive"
  },
  "1229240": {
    "Name": "Chained.Echoes",
    "AppID": 1229240,
    "InstalledBuild": 21147362,
    "LatestDate": "2025-12-11T13:05:54.000Z",
    "Rating": 91,
    "LatestBuild": 21147362,
    "RatingPercent": 89.04910366328916,
    "ReviewsTotal": 7698,
    "ReviewsPositive": 6855,
    "ReviewsNegative": 843,
    "ReviewSummary": "Very Positive"
  },
  "1244090": {
    "Name": "Sea.of.Stars",
    "AppID": 1244090,
    "InstalledBuild": 20404391,
    "LatestDate": "2025-10-15T14:56:31.000Z",
    "Rating": 87,
    "LatestBuild": 20404391,
    "RatingPercent": 89.12280701754386,
    "ReviewsTotal": 14250,
    "ReviewsPositive": 12700,
    "ReviewsNegative": 1550,
    "ReviewSummary": "Very Positive"
  },
  "1262350": {
    "Name": "SIGNALIS",
    "AppID": 1262350,
    "InstalledBuild": 20243420,
    "LatestDate": "2025-10-05T20:23:08.000Z",
    "Rating": 96,
    "LatestBuild": 20243420,
    "RatingPercent": 96.6535371041437,
    "ReviewsTotal": 31735,
    "ReviewsPositive": 30673,
    "ReviewsNegative": 1062,
    "ReviewSummary": "Overwhelmingly Positive"
  },
  "1264280": {
    "Name": "Slipways",
    "AppID": 1264280,
    "InstalledBuild": 15946357,
    "LatestDate": "2024-10-07T12:28:20.000Z",
    "Rating": 92,
    "LatestBuild": 15946357,
    "RatingPercent": 92.89183222958057,
    "ReviewsTotal": 2265,
    "ReviewsPositive": 2104,
    "ReviewsNegative": 161,
    "ReviewSummary": "Very Positive"
  },
  "1277400": {
    "Name": "Monster.Hunter.Stories.2.Wings.of.Ruin",
    "AppID": 1277400,
    "InstalledBuild": 20139678,
    "LatestDate": "2025-11-26T00:59:37.000Z",
    "Rating": 82,
    "LatestBuild": 20139678,
    "RatingPercent": 82.58650365006825,
    "ReviewsTotal": 16849,
    "ReviewsPositive": 13915,
    "ReviewsNegative": 2934,
    "ReviewSummary": "Very Positive"
  },
  "1280930": {
    "Name": "Astral.Ascent",
    "AppID": 1280930,
    "InstalledBuild": 21949048,
    "LatestDate": "2026-03-18T15:43:22.000Z",
    "Rating": 86,
    "LatestBuild": 22399636,
    "RatingPercent": 94.74538192710934,
    "ReviewsTotal": 8012,
    "ReviewsPositive": 7591,
    "ReviewsNegative": 421,
    "ReviewSummary": "Very Positive"
  },
  "1313140": {
    "Name": "Cult.of.the.Lamb",
    "AppID": 1313140,
    "InstalledBuild": 22221801,
    "LatestDate": "2026-03-10T06:14:46.000Z",
    "RatingPercent": 95.82321998094686,
    "ReviewsTotal": 120715,
    "ReviewsPositive": 115673,
    "ReviewsNegative": 5042,
    "ReviewSummary": "Overwhelmingly Positive",
    "LatestBuild": 22221801
  },
  "1336490": {
    "Name": "Against.the.Storm",
    "AppID": 1336490,
    "InstalledBuild": 21522665,
    "LatestDate": "2026-01-19T12:08:28.000Z",
    "Rating": 91,
    "LatestBuild": 21522665,
    "RatingPercent": 94.71720512168235,
    "ReviewsTotal": 35379,
    "ReviewsPositive": 33510,
    "ReviewsNegative": 1869,
    "ReviewSummary": "Very Positive"
  },
  "1361510": {
    "Name": "TMNT.Shredders.Revenge",
    "AppID": 1361510,
    "InstalledBuild": 15664053,
    "LatestDate": "2026-03-19T08:41:37.071Z",
    "Status": "✅ Up-to-date",
    "Rating": 84,
    "RatingPercent": 94.42203366253999,
    "ReviewsTotal": 14378,
    "ReviewsPositive": 13576,
    "ReviewsNegative": 802,
    "ReviewSummary": "Very Positive"
  },
  "1363080": {
    "Name": "Manor.Lords",
    "AppID": 1363080,
    "InstalledBuild": 22368857,
    "LatestDate": "2026-03-18T15:04:10.000Z",
    "Rating": 84,
    "LatestBuild": 22368857,
    "RatingPercent": 84.62671789915373,
    "ReviewsTotal": 84842,
    "ReviewsPositive": 71799,
    "ReviewsNegative": 13043,
    "ReviewSummary": "Very Positive"
  },
  "1369630": {
    "Name": "ENDER.LILIES.Quietus.of.the.Knights",
    "AppID": 1369630,
    "InstalledBuild": 8834157,
    "LatestDate": "2022-06-03T07:45:21.000Z",
    "Rating": 86,
    "LatestBuild": 8834157,
    "RatingPercent": 93.85274051009662,
    "ReviewsTotal": 43678,
    "ReviewsPositive": 40993,
    "ReviewsNegative": 2685,
    "ReviewSummary": "Very Positive"
  },
  "1458140": {
    "Name": "Pacific.Drive",
    "AppID": 1458140,
    "InstalledBuild": 21896301,
    "LatestDate": "2026-02-23T16:58:31.000Z",
    "Rating": 83,
    "LatestBuild": 21896301,
    "RatingPercent": 83.31043400953689,
    "ReviewsTotal": 24746,
    "ReviewsPositive": 20616,
    "ReviewsNegative": 4130,
    "ReviewSummary": "Very Positive"
  },
  "1578650": {
    "Name": "Citizen.Sleeper",
    "AppID": 1578650,
    "InstalledBuild": 21238792,
    "LatestDate": "2025-12-18T10:36:25.000Z",
    "LatestBuild": 21238792,
    "RatingPercent": 92.66130694702125,
    "ReviewsTotal": 9702,
    "ReviewsPositive": 8990,
    "ReviewsNegative": 712,
    "ReviewSummary": "Very Positive"
  },
  "1588550": {
    "Name": "Cairn",
    "AppID": 1588550,
    "InstalledBuild": 21916175,
    "LatestDate": "2026-02-19T12:39:09.000Z",
    "LatestBuild": 21916175,
    "RatingPercent": 94.4336820353868,
    "ReviewsTotal": 15486,
    "ReviewsPositive": 14624,
    "ReviewsNegative": 862,
    "ReviewSummary": "Very Positive"
  },
  "1593030": {
    "Name": "Terra.Nil",
    "AppID": 1593030,
    "InstalledBuild": 19755773,
    "LatestDate": "2025-08-27T14:17:14.000Z",
    "Status": "✅ Up-to-date",
    "Rating": 79,
    "LatestBuild": 19755773,
    "RatingPercent": 87.54225012071463,
    "ReviewsTotal": 8284,
    "ReviewsPositive": 7252,
    "ReviewsNegative": 1032,
    "ReviewSummary": "Very Positive"
  },
  "1601580": {
    "Name": "Frostpunk.2",
    "AppID": 1601580,
    "InstalledBuild": 22054897,
    "LatestDate": "2026-02-24T14:36:23.000Z",
    "LatestBuild": 22054897,
    "RatingPercent": 75.02485583615032,
    "ReviewsTotal": 25145,
    "ReviewsPositive": 18865,
    "ReviewsNegative": 6280,
    "ReviewSummary": "Mostly Positive"
  },
  "1621690": {
    "Name": "Core.Keeper",
    "AppID": 1621690,
    "InstalledBuild": 22329481,
    "LatestDate": "2026-03-16T09:58:09.000Z",
    "Rating": 85,
    "LatestBuild": 22329481,
    "RatingPercent": 92.92236716512886,
    "ReviewsTotal": 62860,
    "ReviewsPositive": 58411,
    "ReviewsNegative": 4449,
    "ReviewSummary": "Very Positive"
  },
  "1637320": {
    "Name": "Dome.Keeper",
    "AppID": 1637320,
    "InstalledBuild": 17779621,
    "LatestDate": "2025-03-19T15:38:50.000Z",
    "Rating": 92,
    "LatestBuild": 17779621,
    "RatingPercent": 92.26774379688402,
    "ReviewsTotal": 19063,
    "ReviewsPositive": 17589,
    "ReviewsNegative": 1474,
    "ReviewSummary": "Very Positive"
  },
  "1649950": {
    "Name": "News.Tower",
    "AppID": 1649950,
    "InstalledBuild": 22124269,
    "LatestDate": "2026-02-27T09:18:59.000Z",
    "Rating": 94,
    "LatestBuild": 22124269,
    "RatingPercent": 94.51263537906136,
    "ReviewsTotal": 4155,
    "ReviewsPositive": 3927,
    "ReviewsNegative": 228,
    "ReviewSummary": "Very Positive"
  },
  "1718570": {
    "Name": "ASTLIBRA.Revision",
    "AppID": 1718570,
    "InstalledBuild": 21868037,
    "LatestDate": "2026-02-10T15:05:36.000Z",
    "Rating": 95,
    "LatestBuild": 21868037,
    "RatingPercent": 95.24239384821131,
    "ReviewsTotal": 29910,
    "ReviewsPositive": 28487,
    "ReviewsNegative": 1423,
    "ReviewSummary": "Overwhelmingly Positive"
  },
  "1755830": {
    "Name": "Astrea.Six.Sided.Oracles",
    "AppID": 1755830,
    "InstalledBuild": 18016665,
    "LatestDate": "2025-04-08T00:59:56.000Z",
    "Rating": 85,
    "LatestBuild": 18016665,
    "RatingPercent": 91.6137805983681,
    "ReviewsTotal": 4412,
    "ReviewsPositive": 4042,
    "ReviewsNegative": 370,
    "ReviewSummary": "Very Positive"
  },
  "1782460": {
    "Name": "Hell.Clock",
    "AppID": 1782460,
    "InstalledBuild": 20968706,
    "LatestDate": "2025-11-27T16:57:03.000Z",
    "Rating": 84,
    "LatestBuild": 20968706,
    "RatingPercent": 83.83392226148409,
    "ReviewsTotal": 3396,
    "ReviewsPositive": 2847,
    "ReviewsNegative": 549,
    "ReviewSummary": "Very Positive"
  },
  "1868140": {
    "Name": "DAVE.THE.DIVER",
    "AppID": 1868140,
    "InstalledBuild": 21569228,
    "LatestDate": "2026-02-19T08:01:05.000Z",
    "Status": "✅ Up-to-date",
    "Rating": 90,
    "LatestBuild": 21917203,
    "RatingPercent": 96.79394396537079,
    "ReviewsTotal": 147159,
    "ReviewsPositive": 142441,
    "ReviewsNegative": 4718,
    "ReviewSummary": "Overwhelmingly Positive"
  },
  "1904480": {
    "Name": "Absolum",
    "AppID": 1904480,
    "InstalledBuild": 22393147,
    "LatestDate": "2026-03-18T14:02:49.000Z",
    "Rating": 87,
    "LatestBuild": 22393147,
    "RatingPercent": 92.59837253371977,
    "ReviewsTotal": 8971,
    "ReviewsPositive": 8307,
    "ReviewsNegative": 664,
    "ReviewSummary": "Very Positive"
  },
  "1940340": {
    "Name": "Darkest.Dungeon.II",
    "AppID": 1940340,
    "InstalledBuild": 20612299,
    "LatestDate": "2026-03-18T22:46:25.000Z",
    "Rating": 81,
    "LatestBuild": 22388413,
    "RatingPercent": 75.23049291558571,
    "ReviewsTotal": 25055,
    "ReviewsPositive": 18849,
    "ReviewsNegative": 6206,
    "ReviewSummary": "Mostly Positive"
  },
  "1942280": {
    "Name": "Brotato",
    "AppID": 1942280,
    "InstalledBuild": 22162077,
    "LatestDate": "2026-03-02T14:49:16.000Z",
    "Status": "✅ Up-to-date",
    "Rating": 96,
    "LatestBuild": 22162077,
    "RatingPercent": 96.59540420023015,
    "ReviewsTotal": 111232,
    "ReviewsPositive": 107445,
    "ReviewsNegative": 3787,
    "ReviewSummary": "Overwhelmingly Positive"
  },
  "1970580": {
    "Name": "Backpack.Hero",
    "AppID": 1970580,
    "InstalledBuild": 15631088,
    "LatestDate": "2024-09-08T17:06:09.000Z",
    "Rating": 76,
    "LatestBuild": 15631088,
    "RatingPercent": 86.97967086156825,
    "ReviewsTotal": 8264,
    "ReviewsPositive": 7188,
    "ReviewsNegative": 1076,
    "ReviewSummary": "Very Positive"
  },
  "1971650": {
    "Name": "OCTOPATH.TRAVELER.II",
    "AppID": 1971650,
    "InstalledBuild": 13399590,
    "LatestDate": "2024-06-05T15:54:48.000Z",
    "Rating": 94,
    "LatestBuild": 13399590,
    "RatingPercent": 94.13138133400643,
    "ReviewsTotal": 15847,
    "ReviewsPositive": 14917,
    "ReviewsNegative": 930,
    "ReviewSummary": "Very Positive"
  },
  "2057760": {
    "Name": "Esoteric.Ebb",
    "AppID": 2057760,
    "InstalledBuild": 22312335,
    "LatestDate": "2026-03-18T14:32:33.000Z",
    "LatestBuild": 22387648,
    "RatingPercent": 96.25881631401411,
    "ReviewsTotal": 3261,
    "ReviewsPositive": 3139,
    "ReviewsNegative": 122,
    "ReviewSummary": "Overwhelmingly Positive"
  },
  "2062430": {
    "Name": "BALL.x.PIT",
    "AppID": 2062430,
    "InstalledBuild": 21684508,
    "LatestDate": "2026-01-28T15:13:31.000Z",
    "Rating": 95,
    "LatestBuild": 21684508,
    "RatingPercent": 95.55772827750383,
    "ReviewsTotal": 23524,
    "ReviewsPositive": 22479,
    "ReviewsNegative": 1045,
    "ReviewSummary": "Overwhelmingly Positive"
  },
  "2066020": {
    "Name": "Soulstone.Survivors",
    "AppID": 2066020,
    "InstalledBuild": 21223726,
    "LatestDate": "2026-03-03T19:46:36.000Z",
    "Status": "⚠️ Update available",
    "Rating": 91,
    "RatingPercent": 91.4131351061384,
    "ReviewsTotal": 26098,
    "ReviewsPositive": 23857,
    "ReviewsNegative": 2241,
    "ReviewSummary": "Very Positive",
    "LatestBuild": 22090199
  },
  "2103140": {
    "Name": "Magicraft",
    "AppID": 2103140,
    "InstalledBuild": 21745630,
    "LatestDate": "2026-03-12T06:24:58.000Z",
    "Rating": 92,
    "LatestBuild": 22306684,
    "RatingPercent": 92.70564541506702,
    "ReviewsTotal": 15889,
    "ReviewsPositive": 14730,
    "ReviewsNegative": 1159,
    "ReviewSummary": "Very Positive"
  },
  "2114740": {
    "Name": "Blasphemous.2",
    "AppID": 2114740,
    "InstalledBuild": 20202981,
    "LatestDate": "2025-10-03T12:41:18.000Z",
    "Status": "✅ Up-to-date",
    "Rating": 83,
    "LatestBuild": 20202981,
    "RatingPercent": 90.52697616060226,
    "ReviewsTotal": 17534,
    "ReviewsPositive": 15873,
    "ReviewsNegative": 1661,
    "ReviewSummary": "Very Positive"
  },
  "2126190": {
    "Name": "Rue.Valley",
    "AppID": 2126190,
    "InstalledBuild": 21669970,
    "LatestDate": "2026-01-28T14:19:07.000Z",
    "Rating": 64,
    "LatestBuild": 21669970,
    "RatingPercent": 64.37086092715232,
    "ReviewsTotal": 1510,
    "ReviewsPositive": 972,
    "ReviewsNegative": 538,
    "ReviewSummary": "Mixed"
  },
  "2179850": {
    "Name": "Cobalt.Core",
    "AppID": 2179850,
    "InstalledBuild": 22309281,
    "LatestDate": "2026-03-12T08:26:21.000Z",
    "Rating": 94,
    "LatestBuild": 22309281,
    "RatingPercent": 96.07795371498173,
    "ReviewsTotal": 4105,
    "ReviewsPositive": 3944,
    "ReviewsNegative": 161,
    "ReviewSummary": "Overwhelmingly Positive"
  },
  "2239150": {
    "Name": "Thronefall",
    "AppID": 2239150,
    "InstalledBuild": 17216593,
    "LatestDate": "2025-02-03T11:39:41.000Z",
    "Rating": 96,
    "LatestBuild": 17216593,
    "RatingPercent": 96.32753235162875,
    "ReviewsTotal": 22410,
    "ReviewsPositive": 21587,
    "ReviewsNegative": 823,
    "ReviewSummary": "Overwhelmingly Positive"
  },
  "2273430": {
    "Name": "BlazBlue.Entropy.Effect",
    "AppID": 2273430,
    "InstalledBuild": 22357607,
    "LatestDate": "2026-03-16T06:33:05.000Z",
    "RatingPercent": 94.30985753013785,
    "ReviewsTotal": 34674,
    "ReviewsPositive": 32701,
    "ReviewsNegative": 1973,
    "ReviewSummary": "Very Positive",
    "LatestBuild": 22357607
  },
  "2308630": {
    "Name": "Dawnfolk",
    "AppID": 2308630,
    "InstalledBuild": 19969051,
    "LatestDate": "2026-03-18T11:02:43.000Z",
    "LatestBuild": 22395882,
    "RatingPercent": 95.82689335394127,
    "ReviewsTotal": 647,
    "ReviewsPositive": 620,
    "ReviewsNegative": 27,
    "ReviewSummary": "Overwhelmingly Positive"
  },
  "2321470": {
    "Name": "Deep.Rock.Galactic.Survivor",
    "AppID": 2321470,
    "InstalledBuild": 21189700,
    "LatestDate": "2025-12-15T14:04:56.000Z",
    "Status": "✅ Up-to-date",
    "Rating": 86,
    "LatestBuild": 21189700,
    "RatingPercent": 86.59367186826451,
    "ReviewsTotal": 46396,
    "ReviewsPositive": 40176,
    "ReviewsNegative": 6220,
    "ReviewSummary": "Very Positive"
  },
  "2334730": {
    "Name": "Death.Must.Die",
    "AppID": 2334730,
    "InstalledBuild": 21650210,
    "LatestDate": "2026-01-26T15:49:03.000Z",
    "Rating": 90,
    "RatingPercent": 90.60013107386948,
    "ReviewsTotal": 21362,
    "ReviewsPositive": 19354,
    "ReviewsNegative": 2008,
    "ReviewSummary": "Very Positive",
    "LatestBuild": 21650210
  },
  "2350790": {
    "Name": "Moonlighter.2.The.Endless.Vault",
    "AppID": 2350790,
    "InstalledBuild": 21465756,
    "LatestDate": "2026-03-13T13:12:39.000Z",
    "LatestBuild": 22315431,
    "Rating": 87,
    "RatingPercent": 86.48648648648648,
    "ReviewsTotal": 2405,
    "ReviewsPositive": 2080,
    "ReviewsNegative": 325,
    "ReviewSummary": "Very Positive"
  },
  "2379780": {
    "Name": "Balatro",
    "AppID": 2379780,
    "InstalledBuild": 17459173,
    "LatestDate": "2025-02-24T18:21:55.000Z",
    "Status": "✅ Up-to-date",
    "LatestBuild": 17459173,
    "Rating": 90,
    "RatingPercent": 97.91757236167689,
    "ReviewsTotal": 186321,
    "ReviewsPositive": 182441,
    "ReviewsNegative": 3880,
    "ReviewSummary": "Overwhelmingly Positive"
  },
  "2442460": {
    "Name": "Citizen.Sleeper.2.Starward.Vector",
    "AppID": 2442460,
    "InstalledBuild": 20765567,
    "LatestDate": "2025-12-12T13:52:21.000Z",
    "RatingPercent": 92.60828625235405,
    "ReviewsTotal": 2124,
    "ReviewsPositive": 1967,
    "ReviewsNegative": 157,
    "ReviewSummary": "Very Positive",
    "LatestBuild": 21164079
  },
  "2444750": {
    "Name": "Shape.of.Dreams",
    "AppID": 2444750,
    "InstalledBuild": 21205645,
    "LatestDate": "2026-03-17T02:03:29.000Z",
    "LatestBuild": 22291018,
    "Rating": 89,
    "RatingPercent": 89.85882220597334,
    "ReviewsTotal": 17779,
    "ReviewsPositive": 15976,
    "ReviewsNegative": 1803,
    "ReviewSummary": "Very Positive"
  },
  "2592160": {
    "Name": "Dispatch",
    "AppID": 2592160,
    "InstalledBuild": 21822905,
    "LatestDate": "2026-02-11T17:59:28.000Z",
    "Rating": 87,
    "RatingPercent": 97.71269631533536,
    "ReviewsTotal": 165741,
    "ReviewsPositive": 161950,
    "ReviewsNegative": 3791,
    "ReviewSummary": "Overwhelmingly Positive",
    "LatestBuild": 21822905
  },
  "2680550": {
    "Name": "Hollywood.Animal",
    "AppID": 2680550,
    "InstalledBuild": 21684216,
    "LatestDate": "2026-03-18T16:14:21.000Z",
    "LatestBuild": 22400438,
    "Rating": 73,
    "RatingPercent": 73.76796714579056,
    "ReviewsTotal": 3896,
    "ReviewsPositive": 2874,
    "ReviewsNegative": 1022,
    "ReviewSummary": "Mostly Positive"
  },
  "2742830": {
    "Name": "Monster.Train.2",
    "AppID": 2742830,
    "InstalledBuild": 21910888,
    "LatestDate": "2026-02-12T23:38:03.000Z",
    "LatestBuild": 21910888,
    "Rating": 87,
    "RatingPercent": 95.54098360655738,
    "ReviewsTotal": 9150,
    "ReviewsPositive": 8742,
    "ReviewsNegative": 408,
    "ReviewSummary": "Overwhelmingly Positive"
  },
  "2756920": {
    "Name": "Keep.Driving",
    "AppID": 2756920,
    "InstalledBuild": 21425122,
    "LatestDate": "2026-01-08T19:43:34.000Z",
    "Status": "✅ Up-to-date",
    "LatestBuild": 21425122,
    "Rating": 94,
    "RatingPercent": 94.25408539799683,
    "ReviewsTotal": 5691,
    "ReviewsPositive": 5364,
    "ReviewsNegative": 327,
    "ReviewSummary": "Very Positive"
  },
  "2868840": {
    "Name": "Slay.the.Spire.2",
    "AppID": 2868840,
    "InstalledBuild": 22238966,
    "LatestDate": "2026-03-17T20:47:42.000Z",
    "LatestBuild": 22340209,
    "RatingPercent": 96.16778010436401,
    "ReviewsTotal": 60174,
    "ReviewsPositive": 57868,
    "ReviewsNegative": 2306,
    "ReviewSummary": "Overwhelmingly Positive"
  },
  "2922410": {
    "Name": "Achilles.Survivor",
    "AppID": 2922410,
    "InstalledBuild": 21901081,
    "LatestDate": "2026-02-18T15:16:18.000Z",
    "LatestBuild": 21901081,
    "Rating": 82,
    "RatingPercent": 83.20340184266477,
    "ReviewsTotal": 1411,
    "ReviewsPositive": 1174,
    "ReviewsNegative": 237,
    "ReviewSummary": "Very Positive"
  },
  "2996040": {
    "Name": "Teenage.Mutant.Ninja.Turtles.Splintered.Fate",
    "AppID": 2996040,
    "InstalledBuild": 21077936,
    "LatestDate": "2026-03-17T19:47:39.000Z",
    "Status": "✅ Up-to-date",
    "LatestBuild": 22385771,
    "Rating": 82,
    "RatingPercent": 82.74834437086092,
    "ReviewsTotal": 3020,
    "ReviewsPositive": 2499,
    "ReviewsNegative": 521,
    "ReviewSummary": "Very Positive"
  },
  "3167020": {
    "Name": "Escape.From.Duckov",
    "AppID": 3167020,
    "InstalledBuild": 21913702,
    "LatestDate": "2026-02-13T06:38:09.000Z",
    "LatestBuild": 21913702,
    "Rating": 84,
    "RatingPercent": 84.41048078160419,
    "ReviewsTotal": 101023,
    "ReviewsPositive": 85274,
    "ReviewsNegative": 15749,
    "ReviewSummary": "Very Positive"
  },
  "3405340": {
    "Name": "Megabonk",
    "AppID": 3405340,
    "InstalledBuild": 21750826,
    "LatestDate": "2026-02-04T16:05:58.000Z",
    "Rating": 95,
    "RatingPercent": 94.80260885466404,
    "ReviewsTotal": 98434,
    "ReviewsPositive": 93318,
    "ReviewsNegative": 5116,
    "ReviewSummary": "Very Positive",
    "LatestBuild": 21750826
  },
  "3467710": {
    "Name": "Wall.World.2",
    "AppID": 3467710,
    "InstalledBuild": 20888272,
    "LatestDate": "2025-11-21T10:59:42.000Z",
    "LatestBuild": 20888272,
    "Rating": 77,
    "RatingPercent": 76.28607277289838,
    "ReviewsTotal": 1594,
    "ReviewsPositive": 1216,
    "ReviewsNegative": 378,
    "ReviewSummary": "Mostly Positive"
  },
  "3483740": {
    "Name": "Cast.n.Chill",
    "AppID": 3483740,
    "InstalledBuild": 22258338,
    "LatestDate": "2026-03-09T10:11:29.000Z",
    "Rating": 95,
    "RatingPercent": 95.29360967184802,
    "ReviewsTotal": 6948,
    "ReviewsPositive": 6621,
    "ReviewsNegative": 327,
    "ReviewSummary": "Overwhelmingly Positive",
    "LatestBuild": 22258338
  },
  "3631290": {
    "Name": "Slots.and.Daggers",
    "AppID": 3631290,
    "InstalledBuild": 20648272,
    "LatestDate": "2025-11-03T11:49:07.000Z",
    "Rating": 94,
    "RatingPercent": 94.66057646873523,
    "ReviewsTotal": 6349,
    "ReviewsPositive": 6010,
    "ReviewsNegative": 339,
    "ReviewSummary": "Very Positive",
    "LatestBuild": 20648272
  },
  "4035270": {
    "Name": "Space.Rock.Breaker",
    "AppID": 4035270,
    "InstalledBuild": 21315276,
    "LatestDate": "2026-02-06T02:56:57.000Z",
    "RatingPercent": 96.98401162790698,
    "ReviewsTotal": 2752,
    "ReviewsPositive": 2669,
    "ReviewsNegative": 83,
    "ReviewSummary": "Overwhelmingly Positive",
    "LatestBuild": 21809434
  },
  "4038320": {
    "Name": "This.Aint.Even.Poker.Ya.Joker",
    "AppID": 4038320,
    "InstalledBuild": 21177577,
    "LatestDate": "2025-12-15T06:14:28.000Z",
    "LatestBuild": 21177577,
    "Rating": 89,
    "RatingPercent": 88.10955243820975,
    "ReviewsTotal": 1497,
    "ReviewsPositive": 1319,
    "ReviewsNegative": 178,
    "ReviewSummary": "Very Positive"
  }
}