{
  "257850": {
    "Name": "Hyper.Light.Drifter",
    "AppID": 257850,
    "InstalledBuild": 10930509,
    "LatestDate": "2023-04-04T19:48:08.000Z",
    "Rating": 84,
    "LatestBuild": 10930509,
    "RatingPercent": 92.97018970189703,
    "ReviewsTotal": 18450,
    "ReviewsPositive": 17153,
    "ReviewsNegative": 1297,
    "ReviewSummary": "Very Positive"
  },
  "261570": {
    "Name": "Ori.and.the.Blind.Forest",
    "AppID": 261570,
    "InstalledBuild": 814852,
    "LatestDate": "2026-03-21T18:51:18.283Z",
    "LatestBuild": 814852,
    "RatingPercent": 94.01330002700513,
    "ReviewsTotal": 59248,
    "ReviewsPositive": 55701,
    "ReviewsNegative": 3547,
    "ReviewSummary": "Very Positive"
  },
  "268910": {
    "Name": "Cuphead",
    "AppID": 268910,
    "InstalledBuild": 20241530,
    "LatestDate": "2025-10-03T22:10:37.000Z",
    "Rating": 88,
    "LatestBuild": 20241530,
    "RatingPercent": 96.24461227818118,
    "ReviewsTotal": 206024,
    "ReviewsPositive": 198287,
    "ReviewsNegative": 7737,
    "ReviewSummary": "Overwhelmingly Positive"
  },
  "323190": {
    "Name": "Frostpunk",
    "AppID": 323190,
    "InstalledBuild": 20303936,
    "LatestDate": "2025-10-20T09:42:34.000Z",
    "LatestBuild": 20303936,
    "RatingPercent": 92.71374060221392,
    "ReviewsTotal": 132345,
    "ReviewsPositive": 122702,
    "ReviewsNegative": 9643,
    "ReviewSummary": "Very Positive"
  },
  "330020": {
    "Name": "Children.of.Morta",
    "AppID": 330020,
    "InstalledBuild": 8334433,
    "LatestDate": "2022-03-08T16:02:23.000Z",
    "Rating": 82,
    "LatestBuild": 8334433,
    "RatingPercent": 88.50880695683038,
    "ReviewsTotal": 22539,
    "ReviewsPositive": 19949,
    "ReviewsNegative": 2590,
    "ReviewSummary": "Very Positive"
  },
  "367520": {
    "Name": "Hollow.Knight",
    "AppID": 367520,
    "InstalledBuild": 21656419,
    "LatestDate": "2026-02-05T23:18:23.000Z",
    "Status": "✅ Up-to-date",
    "Rating": 87,
    "LatestBuild": 21656419,
    "RatingPercent": 96.91451789459454,
    "ReviewsTotal": 532591,
    "ReviewsPositive": 516158,
    "ReviewsNegative": 16433,
    "ReviewSummary": "Overwhelmingly Positive"
  },
  "368340": {
    "Name": "CrossCode",
    "AppID": 368340,
    "InstalledBuild": 20004663,
    "LatestDate": "2025-09-20T13:15:00.000Z",
    "Rating": 86,
    "LatestBuild": 20004663,
    "RatingPercent": 92.86484033804095,
    "ReviewsTotal": 17631,
    "ReviewsPositive": 16373,
    "ReviewsNegative": 1258,
    "ReviewSummary": "Very Positive"
  },
  "394310": {
    "Name": "Punch.Club",
    "AppID": 394310,
    "InstalledBuild": 11412837,
    "LatestDate": "2024-01-26T08:51:08.000Z",
    "Rating": 73,
    "LatestBuild": 1734185,
    "RatingPercent": 80.49333160688852,
    "ReviewsTotal": 15446,
    "ReviewsPositive": 12433,
    "ReviewsNegative": 3013,
    "ReviewSummary": "Very Positive"
  },
  "503560": {
    "Name": "911.Operator",
    "AppID": 503560,
    "InstalledBuild": 7533741,
    "LatestDate": "2021-10-14T15:35:34.000Z",
    "Rating": 68,
    "LatestBuild": 7533741,
    "RatingPercent": 88.62834612990247,
    "ReviewsTotal": 19276,
    "ReviewsPositive": 17084,
    "ReviewsNegative": 2192,
    "ReviewSummary": "Very Positive"
  },
  "504230": {
    "Name": "Celeste",
    "AppID": 504230,
    "InstalledBuild": 17282758,
    "LatestDate": "2025-02-07T17:00:06.000Z",
    "Rating": 88,
    "LatestBuild": 17282758,
    "RatingPercent": 97.42152547657548,
    "ReviewsTotal": 137911,
    "ReviewsPositive": 134355,
    "ReviewsNegative": 3556,
    "ReviewSummary": "Overwhelmingly Positive"
  },
  "553420": {
    "Name": "Tunic",
    "AppID": 553420,
    "InstalledBuild": 10650562,
    "LatestDate": "2023-03-02T20:14:47.000Z",
    "Status": "✅ Up-to-date",
    "Rating": 85,
    "LatestBuild": 10650562,
    "RatingPercent": 91.46825396825396,
    "ReviewsTotal": 17136,
    "ReviewsPositive": 15674,
    "ReviewsNegative": 1462,
    "ReviewSummary": "Very Positive"
  },
  "588650": {
    "Name": "Dead.Cells",
    "AppID": 588650,
    "InstalledBuild": 15492902,
    "LatestDate": "2024-08-27T08:14:59.000Z",
    "Status": "✅ Up-to-date",
    "Rating": 89,
    "LatestBuild": 15492902,
    "RatingPercent": 97.0447517031194,
    "ReviewsTotal": 178496,
    "ReviewsPositive": 173221,
    "ReviewsNegative": 5275,
    "ReviewSummary": "Overwhelmingly Positive"
  },
  "632360": {
    "Name": "Risk.of.Rain.2",
    "AppID": 632360,
    "InstalledBuild": 21587608,
    "LatestDate": "2026-03-22T17:24:41.368Z",
    "RatingPercent": 93.75302071262614,
    "ReviewsTotal": 343462,
    "ReviewsPositive": 322006,
    "ReviewsNegative": 21456,
    "ReviewSummary": "Very Positive"
  },
  "632470": {
    "Name": "Disco.Elysium",
    "AppID": 632470,
    "InstalledBuild": 21464562,
    "LatestDate": "2026-01-23T14:24:58.000Z",
    "Rating": 97,
    "LatestBuild": 21464562,
    "RatingPercent": 92.70509159742052,
    "ReviewsTotal": 124676,
    "ReviewsPositive": 115581,
    "ReviewsNegative": 9095,
    "ReviewSummary": "Very Positive"
  },
  "653530": {
    "Name": "Return.of.the.Obra.Dinn",
    "AppID": 653530,
    "InstalledBuild": 9550393,
    "LatestDate": "2022-09-20T07:24:13.000Z",
    "Rating": 89,
    "LatestBuild": 9550393,
    "RatingPercent": 96.72627978155194,
    "ReviewsTotal": 33326,
    "ReviewsPositive": 32235,
    "ReviewsNegative": 1091,
    "ReviewSummary": "Overwhelmingly Positive"
  },
  "686060": {
    "Name": "Mewgenics",
    "AppID": 686060,
    "InstalledBuild": 22384947,
    "LatestDate": "2026-03-18T00:04:58.000Z",
    "LatestBuild": 22384947,
    "RatingPercent": 92.141507557677,
    "ReviewsTotal": 40224,
    "ReviewsPositive": 37063,
    "ReviewsNegative": 3161,
    "ReviewSummary": "Very Positive"
  },
  "690830": {
    "Name": "Foundation",
    "AppID": 690830,
    "InstalledBuild": 22062501,
    "LatestDate": "2026-02-24T15:06:13.000Z",
    "Rating": 84,
    "LatestBuild": 22062501,
    "RatingPercent": 86.38399522245447,
    "ReviewsTotal": 23443,
    "ReviewsPositive": 20251,
    "ReviewsNegative": 3192,
    "ReviewSummary": "Very Positive"
  },
  "692850": {
    "Name": "Bloodstained.Ritual.of.the.Night",
    "AppID": 692850,
    "InstalledBuild": 20844919,
    "LatestDate": "2025-12-23T15:37:31.000Z",
    "Rating": 93,
    "LatestBuild": 20844919,
    "RatingPercent": 93.35781613416574,
    "ReviewsTotal": 40845,
    "ReviewsPositive": 38132,
    "ReviewsNegative": 2713,
    "ReviewSummary": "Very Positive"
  },
  "774181": {
    "Name": "Rhythm.Doctor",
    "AppID": 774181,
    "InstalledBuild": 22372042,
    "LatestDate": "2026-03-17T00:28:03.000Z",
    "Rating": 87,
    "LatestBuild": 22372042,
    "RatingPercent": 98.22510486251359,
    "ReviewsTotal": 25748,
    "ReviewsPositive": 25291,
    "ReviewsNegative": 457,
    "ReviewSummary": "Overwhelmingly Positive"
  },
  "774361": {
    "Name": "Blasphemous",
    "AppID": 774361,
    "InstalledBuild": 20206233,
    "LatestDate": "2025-10-03T09:46:58.000Z",
    "Status": "✅ Up-to-date",
    "Rating": 77,
    "LatestBuild": 20206233,
    "RatingPercent": 89.81330316010668,
    "ReviewsTotal": 61865,
    "ReviewsPositive": 55563,
    "ReviewsNegative": 6302,
    "ReviewSummary": "Very Positive"
  },
  "787480": {
    "Name": "Phoenix.Wright.Ace.Attorney.Trilogy",
    "AppID": 787480,
    "InstalledBuild": 20282248,
    "LatestDate": "2025-11-19T01:00:38.000Z",
    "LatestBuild": 20282248,
    "RatingPercent": 97.56367142487595,
    "ReviewsTotal": 42523,
    "ReviewsPositive": 41487,
    "ReviewsNegative": 1036,
    "ReviewSummary": "Overwhelmingly Positive"
  },
  "867210": {
    "Name": "Songs.of.Conquest",
    "AppID": 867210,
    "InstalledBuild": 22401468,
    "LatestDate": "2026-03-18T18:46:13.000Z",
    "Rating": 85,
    "LatestBuild": 22401468,
    "RatingPercent": 85.76115986264784,
    "ReviewsTotal": 13105,
    "ReviewsPositive": 11239,
    "ReviewsNegative": 1866,
    "ReviewSummary": "Very Positive"
  },
  "894020": {
    "Name": "Deaths.Door",
    "AppID": 894020,
    "InstalledBuild": 7480208,
    "LatestDate": "2021-10-05T10:21:41.000Z",
    "Rating": 85,
    "LatestBuild": 7480208,
    "RatingPercent": 93.20152453549309,
    "ReviewsTotal": 20990,
    "ReviewsPositive": 19563,
    "ReviewsNegative": 1427,
    "ReviewSummary": "Very Positive"
  },
  "921570": {
    "Name": "Octopath.Traveler",
    "AppID": 921570,
    "InstalledBuild": 5272616,
    "LatestDate": "2020-07-22T16:55:34.000Z",
    "Rating": 80,
    "RatingPercent": 85.79823702252693,
    "ReviewsTotal": 16336,
    "ReviewsPositive": 14016,
    "ReviewsNegative": 2320,
    "ReviewSummary": "Very Positive",
    "LatestBuild": 5272616
  },
  "1030300": {
    "Name": "Hollow.Knight.Silksong",
    "AppID": 1030300,
    "InstalledBuild": 22372218,
    "LatestDate": "2026-03-20T08:32:35.000Z",
    "Status": "✅ Up-to-date",
    "Rating": 90,
    "LatestBuild": 22428725,
    "RatingPercent": 89.09954152728878,
    "ReviewsTotal": 398497,
    "ReviewsPositive": 355059,
    "ReviewsNegative": 43438,
    "ReviewSummary": "Very Positive"
  },
  "1057090": {
    "Name": "Ori.and.the.Will.of.the.Wisps",
    "AppID": 1057090,
    "InstalledBuild": 5845748,
    "LatestDate": "2020-11-19T23:05:46.000Z",
    "LatestBuild": 5845748,
    "RatingPercent": 96.54227238083251,
    "ReviewsTotal": 143013,
    "ReviewsPositive": 138068,
    "ReviewsNegative": 4945,
    "ReviewSummary": "Overwhelmingly Positive"
  },
  "1161590": {
    "Name": "Punch.Club.2.Fast.Forward",
    "AppID": 1161590,
    "InstalledBuild": 20464979,
    "LatestDate": "2025-10-20T14:12:49.000Z",
    "Status": "✅ Up-to-date",
    "Rating": 82,
    "LatestBuild": 20464979,
    "RatingPercent": 82.5278810408922,
    "ReviewsTotal": 4304,
    "ReviewsPositive": 3552,
    "ReviewsNegative": 752,
    "ReviewSummary": "Very Positive"
  },
  "1210320": {
    "Name": "Potion.Craft.Alchemist.Simulator",
    "AppID": 1210320,
    "InstalledBuild": 18969694,
    "LatestDate": "2025-06-26T16:32:29.000Z",
    "LatestBuild": 18969694,
    "RatingPercent": 92.83161656506202,
    "ReviewsTotal": 42813,
    "ReviewsPositive": 39744,
    "ReviewsNegative": 3069,
    "ReviewSummary": "Very Positive"
  },
  "1229240": {
    "Name": "Chained.Echoes",
    "AppID": 1229240,
    "InstalledBuild": 21147362,
    "LatestDate": "2025-12-11T13:05:54.000Z",
    "Rating": 91,
    "LatestBuild": 21147362,
    "RatingPercent": 89.00700025926886,
    "ReviewsTotal": 7714,
    "ReviewsPositive": 6866,
    "ReviewsNegative": 848,
    "ReviewSummary": "Very Positive"
  },
  "1244090": {
    "Name": "Sea.of.Stars",
    "AppID": 1244090,
    "InstalledBuild": 20404391,
    "LatestDate": "2025-10-15T14:56:31.000Z",
    "Rating": 87,
    "LatestBuild": 20404391,
    "RatingPercent": 89.12189647916959,
    "ReviewsTotal": 14258,
    "ReviewsPositive": 12707,
    "ReviewsNegative": 1551,
    "ReviewSummary": "Very Positive"
  },
  "1262350": {
    "Name": "SIGNALIS",
    "AppID": 1262350,
    "InstalledBuild": 20243420,
    "LatestDate": "2025-10-05T20:23:08.000Z",
    "Rating": 96,
    "LatestBuild": 20243420,
    "RatingPercent": 96.64602520981988,
    "ReviewsTotal": 31813,
    "ReviewsPositive": 30746,
    "ReviewsNegative": 1067,
    "ReviewSummary": "Overwhelmingly Positive"
  },
  "1264280": {
    "Name": "Slipways",
    "AppID": 1264280,
    "InstalledBuild": 15946357,
    "LatestDate": "2024-10-07T12:28:20.000Z",
    "Rating": 92,
    "LatestBuild": 15946357,
    "RatingPercent": 92.89183222958057,
    "ReviewsTotal": 2265,
    "ReviewsPositive": 2104,
    "ReviewsNegative": 161,
    "ReviewSummary": "Very Positive"
  },
  "1277400": {
    "Name": "Monster.Hunter.Stories.2.Wings.of.Ruin",
    "AppID": 1277400,
    "InstalledBuild": 20139678,
    "LatestDate": "2025-11-26T00:59:37.000Z",
    "Rating": 82,
    "LatestBuild": 20139678,
    "RatingPercent": 82.5873006462323,
    "ReviewsTotal": 16867,
    "ReviewsPositive": 13930,
    "ReviewsNegative": 2937,
    "ReviewSummary": "Very Positive"
  },
  "1280930": {
    "Name": "Astral.Ascent",
    "AppID": 1280930,
    "InstalledBuild": 22399636,
    "LatestDate": "2026-03-18T15:43:22.000Z",
    "Rating": 86,
    "LatestBuild": 22399636,
    "RatingPercent": 94.75258631434626,
    "ReviewsTotal": 8023,
    "ReviewsPositive": 7602,
    "ReviewsNegative": 421,
    "ReviewSummary": "Very Positive"
  },
  "1313140": {
    "Name": "Cult.of.the.Lamb",
    "AppID": 1313140,
    "InstalledBuild": 22221801,
    "LatestDate": "2026-03-10T06:14:46.000Z",
    "RatingPercent": 95.82695854249539,
    "ReviewsTotal": 120919,
    "ReviewsPositive": 115873,
    "ReviewsNegative": 5046,
    "ReviewSummary": "Overwhelmingly Positive",
    "LatestBuild": 22221801
  },
  "1336490": {
    "Name": "Against.the.Storm",
    "AppID": 1336490,
    "InstalledBuild": 21522665,
    "LatestDate": "2026-01-19T12:08:28.000Z",
    "Rating": 91,
    "LatestBuild": 21522665,
    "RatingPercent": 94.7099361690109,
    "ReviewsTotal": 35406,
    "ReviewsPositive": 33533,
    "ReviewsNegative": 1873,
    "ReviewSummary": "Very Positive"
  },
  "1361510": {
    "Name": "TMNT.Shredders.Revenge",
    "AppID": 1361510,
    "InstalledBuild": 15664053,
    "LatestDate": "2026-03-22T17:25:10.898Z",
    "Status": "✅ Up-to-date",
    "Rating": 84,
    "RatingPercent": 94.41356309060589,
    "ReviewsTotal": 14392,
    "ReviewsPositive": 13588,
    "ReviewsNegative": 804,
    "ReviewSummary": "Very Positive"
  },
  "1363080": {
    "Name": "Manor.Lords",
    "AppID": 1363080,
    "InstalledBuild": 22368857,
    "LatestDate": "2026-03-18T15:04:10.000Z",
    "Rating": 84,
    "LatestBuild": 22368857,
    "RatingPercent": 84.62542171648897,
    "ReviewsTotal": 85069,
    "ReviewsPositive": 71990,
    "ReviewsNegative": 13079,
    "ReviewSummary": "Very Positive"
  },
  "1369630": {
    "Name": "ENDER.LILIES.Quietus.of.the.Knights",
    "AppID": 1369630,
    "InstalledBuild": 8834157,
    "LatestDate": "2022-06-03T07:45:21.000Z",
    "Rating": 86,
    "LatestBuild": 8834157,
    "RatingPercent": 93.85234653737078,
    "ReviewsTotal": 43724,
    "ReviewsPositive": 41036,
    "ReviewsNegative": 2688,
    "ReviewSummary": "Very Positive"
  },
  "1458140": {
    "Name": "Pacific.Drive",
    "AppID": 1458140,
    "InstalledBuild": 21896301,
    "LatestDate": "2026-02-23T16:58:31.000Z",
    "Rating": 83,
    "LatestBuild": 21896301,
    "RatingPercent": 83.31316065520859,
    "ReviewsTotal": 24786,
    "ReviewsPositive": 20650,
    "ReviewsNegative": 4136,
    "ReviewSummary": "Very Positive"
  },
  "1578650": {
    "Name": "Citizen.Sleeper",
    "AppID": 1578650,
    "InstalledBuild": 21238792,
    "LatestDate": "2025-12-18T10:36:25.000Z",
    "LatestBuild": 21238792,
    "RatingPercent": 92.6440329218107,
    "ReviewsTotal": 9720,
    "ReviewsPositive": 9005,
    "ReviewsNegative": 715,
    "ReviewSummary": "Very Positive"
  },
  "1588550": {
    "Name": "Cairn",
    "AppID": 1588550,
    "InstalledBuild": 21916175,
    "LatestDate": "2026-02-19T12:39:09.000Z",
    "LatestBuild": 21916175,
    "RatingPercent": 94.42997777072087,
    "ReviewsTotal": 15745,
    "ReviewsPositive": 14868,
    "ReviewsNegative": 877,
    "ReviewSummary": "Very Positive"
  },
  "1593030": {
    "Name": "Terra.Nil",
    "AppID": 1593030,
    "InstalledBuild": 19755773,
    "LatestDate": "2026-03-20T13:20:39.000Z",
    "Status": "✅ Up-to-date",
    "Rating": 79,
    "LatestBuild": 22309377,
    "RatingPercent": 87.51656826123629,
    "ReviewsTotal": 8299,
    "ReviewsPositive": 7263,
    "ReviewsNegative": 1036,
    "ReviewSummary": "Very Positive"
  },
  "1601580": {
    "Name": "Frostpunk.2",
    "AppID": 1601580,
    "InstalledBuild": 22054897,
    "LatestDate": "2026-02-24T14:36:23.000Z",
    "LatestBuild": 22054897,
    "RatingPercent": 75.04567479545635,
    "ReviewsTotal": 25178,
    "ReviewsPositive": 18895,
    "ReviewsNegative": 6283,
    "ReviewSummary": "Mostly Positive"
  },
  "1621690": {
    "Name": "Core.Keeper",
    "AppID": 1621690,
    "InstalledBuild": 22329481,
    "LatestDate": "2026-03-16T09:58:09.000Z",
    "Rating": 85,
    "LatestBuild": 22329481,
    "RatingPercent": 92.92362920134697,
    "ReviewsTotal": 62956,
    "ReviewsPositive": 58501,
    "ReviewsNegative": 4455,
    "ReviewSummary": "Very Positive"
  },
  "1637320": {
    "Name": "Dome.Keeper",
    "AppID": 1637320,
    "InstalledBuild": 17779621,
    "LatestDate": "2025-03-19T15:38:50.000Z",
    "Rating": 92,
    "LatestBuild": 17779621,
    "RatingPercent": 92.26707100282339,
    "ReviewsTotal": 19126,
    "ReviewsPositive": 17647,
    "ReviewsNegative": 1479,
    "ReviewSummary": "Very Positive"
  },
  "1649950": {
    "Name": "News.Tower",
    "AppID": 1649950,
    "InstalledBuild": 22124269,
    "LatestDate": "2026-02-27T09:18:59.000Z",
    "Rating": 94,
    "LatestBuild": 22124269,
    "RatingPercent": 94.48176583493282,
    "ReviewsTotal": 4168,
    "ReviewsPositive": 3938,
    "ReviewsNegative": 230,
    "ReviewSummary": "Very Positive"
  },
  "1718570": {
    "Name": "ASTLIBRA.Revision",
    "AppID": 1718570,
    "InstalledBuild": 21868037,
    "LatestDate": "2026-02-10T15:05:36.000Z",
    "Rating": 95,
    "LatestBuild": 21868037,
    "RatingPercent": 95.24525025877325,
    "ReviewsTotal": 29949,
    "ReviewsPositive": 28525,
    "ReviewsNegative": 1424,
    "ReviewSummary": "Overwhelmingly Positive"
  },
  "1755830": {
    "Name": "Astrea.Six.Sided.Oracles",
    "AppID": 1755830,
    "InstalledBuild": 18016665,
    "LatestDate": "2025-04-08T00:59:56.000Z",
    "Rating": 85,
    "LatestBuild": 18016665,
    "RatingPercent": 91.62516976007244,
    "ReviewsTotal": 4418,
    "ReviewsPositive": 4048,
    "ReviewsNegative": 370,
    "ReviewSummary": "Very Positive"
  },
  "1782460": {
    "Name": "Hell.Clock",
    "AppID": 1782460,
    "InstalledBuild": 20968706,
    "LatestDate": "2025-11-27T16:57:03.000Z",
    "Rating": 84,
    "LatestBuild": 20968706,
    "RatingPercent": 83.84819064430715,
    "ReviewsTotal": 3399,
    "ReviewsPositive": 2850,
    "ReviewsNegative": 549,
    "ReviewSummary": "Very Positive"
  },
  "1868140": {
    "Name": "Dave.the.Diver",
    "AppID": 1868140,
    "InstalledBuild": 21917203,
    "LatestDate": "2026-02-19T08:01:05.000Z",
    "Status": "✅ Up-to-date",
    "Rating": 90,
    "LatestBuild": 21917203,
    "RatingPercent": 96.79050385492452,
    "ReviewsTotal": 147344,
    "ReviewsPositive": 142615,
    "ReviewsNegative": 4729,
    "ReviewSummary": "Overwhelmingly Positive"
  },
  "1904480": {
    "Name": "Absolum",
    "AppID": 1904480,
    "InstalledBuild": 22393147,
    "LatestDate": "2026-03-18T14:02:49.000Z",
    "Rating": 87,
    "LatestBuild": 22393147,
    "RatingPercent": 92.59464860663928,
    "ReviewsTotal": 9007,
    "ReviewsPositive": 8340,
    "ReviewsNegative": 667,
    "ReviewSummary": "Very Positive"
  },
  "1940340": {
    "Name": "Darkest.Dungeon.II",
    "AppID": 1940340,
    "InstalledBuild": 22388413,
    "LatestDate": "2026-03-18T22:46:25.000Z",
    "Rating": 81,
    "LatestBuild": 22388413,
    "RatingPercent": 75.1973526831991,
    "ReviewsTotal": 25082,
    "ReviewsPositive": 18861,
    "ReviewsNegative": 6221,
    "ReviewSummary": "Mostly Positive"
  },
  "1942280": {
    "Name": "Brotato",
    "AppID": 1942280,
    "InstalledBuild": 22162077,
    "LatestDate": "2026-03-02T14:49:16.000Z",
    "Status": "✅ Up-to-date",
    "Rating": 96,
    "LatestBuild": 22162077,
    "RatingPercent": 96.59179696270286,
    "ReviewsTotal": 111349,
    "ReviewsPositive": 107554,
    "ReviewsNegative": 3795,
    "ReviewSummary": "Overwhelmingly Positive"
  },
  "1970580": {
    "Name": "Backpack.Hero",
    "AppID": 1970580,
    "InstalledBuild": 15631088,
    "LatestDate": "2024-09-08T17:06:09.000Z",
    "Rating": 76,
    "LatestBuild": 15631088,
    "RatingPercent": 86.98017408123792,
    "ReviewsTotal": 8272,
    "ReviewsPositive": 7195,
    "ReviewsNegative": 1077,
    "ReviewSummary": "Very Positive"
  },
  "1971650": {
    "Name": "OCTOPATH.TRAVELER.II",
    "AppID": 1971650,
    "InstalledBuild": 13399590,
    "LatestDate": "2024-06-05T15:54:48.000Z",
    "Rating": 94,
    "LatestBuild": 13399590,
    "RatingPercent": 94.12431513319478,
    "ReviewsTotal": 15879,
    "ReviewsPositive": 14946,
    "ReviewsNegative": 933,
    "ReviewSummary": "Very Positive"
  },
  "2057760": {
    "Name": "Esoteric.Ebb",
    "AppID": 2057760,
    "InstalledBuild": 22416378,
    "LatestDate": "2026-03-19T14:32:43.000Z",
    "LatestBuild": 22416378,
    "RatingPercent": 96.37462235649546,
    "ReviewsTotal": 3641,
    "ReviewsPositive": 3509,
    "ReviewsNegative": 132,
    "ReviewSummary": "Overwhelmingly Positive"
  },
  "2062430": {
    "Name": "BALL.x.PIT",
    "AppID": 2062430,
    "InstalledBuild": 21684508,
    "LatestDate": "2026-01-28T15:13:31.000Z",
    "Rating": 95,
    "LatestBuild": 21684508,
    "RatingPercent": 95.56383338977311,
    "ReviewsTotal": 23624,
    "ReviewsPositive": 22576,
    "ReviewsNegative": 1048,
    "ReviewSummary": "Overwhelmingly Positive"
  },
  "2066020": {
    "Name": "Soulstone.Survivors",
    "AppID": 2066020,
    "InstalledBuild": 21223726,
    "LatestDate": "2026-03-03T19:46:36.000Z",
    "Status": "⚠️ Update available",
    "Rating": 91,
    "RatingPercent": 91.40690817186183,
    "ReviewsTotal": 26114,
    "ReviewsPositive": 23870,
    "ReviewsNegative": 2244,
    "ReviewSummary": "Very Positive",
    "LatestBuild": 22090199
  },
  "2103140": {
    "Name": "Magicraft",
    "AppID": 2103140,
    "InstalledBuild": 21745630,
    "LatestDate": "2026-03-20T03:21:39.000Z",
    "Rating": 92,
    "LatestBuild": 22426655,
    "RatingPercent": 92.71127866792335,
    "ReviewsTotal": 15915,
    "ReviewsPositive": 14755,
    "ReviewsNegative": 1160,
    "ReviewSummary": "Very Positive"
  },
  "2114740": {
    "Name": "Blasphemous.2",
    "AppID": 2114740,
    "InstalledBuild": 20202981,
    "LatestDate": "2025-10-03T12:41:18.000Z",
    "Status": "✅ Up-to-date",
    "Rating": 83,
    "LatestBuild": 20202981,
    "RatingPercent": 90.52224371373308,
    "ReviewsTotal": 17578,
    "ReviewsPositive": 15912,
    "ReviewsNegative": 1666,
    "ReviewSummary": "Very Positive"
  },
  "2126190": {
    "Name": "Rue.Valley",
    "AppID": 2126190,
    "InstalledBuild": 21669970,
    "LatestDate": "2026-01-28T14:19:07.000Z",
    "Rating": 64,
    "LatestBuild": 21669970,
    "RatingPercent": 64.5118733509235,
    "ReviewsTotal": 1516,
    "ReviewsPositive": 978,
    "ReviewsNegative": 538,
    "ReviewSummary": "Mixed"
  },
  "2179850": {
    "Name": "Cobalt.Core",
    "AppID": 2179850,
    "InstalledBuild": 22309281,
    "LatestDate": "2026-03-12T08:26:21.000Z",
    "Rating": 94,
    "LatestBuild": 22309281,
    "RatingPercent": 96.07986364743122,
    "ReviewsTotal": 4107,
    "ReviewsPositive": 3946,
    "ReviewsNegative": 161,
    "ReviewSummary": "Overwhelmingly Positive"
  },
  "2239150": {
    "Name": "Thronefall",
    "AppID": 2239150,
    "InstalledBuild": 17216593,
    "LatestDate": "2025-02-03T11:39:41.000Z",
    "Rating": 96,
    "LatestBuild": 17216593,
    "RatingPercent": 96.3302752293578,
    "ReviewsTotal": 22454,
    "ReviewsPositive": 21630,
    "ReviewsNegative": 824,
    "ReviewSummary": "Overwhelmingly Positive"
  },
  "2273430": {
    "Name": "BlazBlue.Entropy.Effect",
    "AppID": 2273430,
    "InstalledBuild": 22357607,
    "LatestDate": "2026-03-16T06:33:05.000Z",
    "RatingPercent": 94.30439918181557,
    "ReviewsTotal": 34711,
    "ReviewsPositive": 32734,
    "ReviewsNegative": 1977,
    "ReviewSummary": "Very Positive",
    "LatestBuild": 22357607
  },
  "2308630": {
    "Name": "Dawnfolk",
    "AppID": 2308630,
    "InstalledBuild": 22395882,
    "LatestDate": "2026-03-18T11:02:43.000Z",
    "LatestBuild": 22395882,
    "RatingPercent": 95.54531490015361,
    "ReviewsTotal": 651,
    "ReviewsPositive": 622,
    "ReviewsNegative": 29,
    "ReviewSummary": "Overwhelmingly Positive"
  },
  "2321470": {
    "Name": "Deep.Rock.Galactic.Survivor",
    "AppID": 2321470,
    "InstalledBuild": 21189700,
    "LatestDate": "2025-12-15T14:04:56.000Z",
    "Status": "✅ Up-to-date",
    "Rating": 86,
    "LatestBuild": 21189700,
    "RatingPercent": 86.60062452891138,
    "ReviewsTotal": 46435,
    "ReviewsPositive": 40213,
    "ReviewsNegative": 6222,
    "ReviewSummary": "Very Positive"
  },
  "2334730": {
    "Name": "Death.Must.Die",
    "AppID": 2334730,
    "InstalledBuild": 21650210,
    "LatestDate": "2026-01-26T15:49:03.000Z",
    "Rating": 90,
    "RatingPercent": 90.59120909984553,
    "ReviewsTotal": 21363,
    "ReviewsPositive": 19353,
    "ReviewsNegative": 2010,
    "ReviewSummary": "Very Positive",
    "LatestBuild": 21650210
  },
  "2350790": {
    "Name": "Moonlighter.2.The.Endless.Vault",
    "AppID": 2350790,
    "InstalledBuild": 22315431,
    "LatestDate": "2026-03-13T13:12:39.000Z",
    "LatestBuild": 22315431,
    "Rating": 87,
    "RatingPercent": 86.39149979566817,
    "ReviewsTotal": 2447,
    "ReviewsPositive": 2114,
    "ReviewsNegative": 333,
    "ReviewSummary": "Very Positive"
  },
  "2379780": {
    "Name": "Balatro",
    "AppID": 2379780,
    "InstalledBuild": 17459173,
    "LatestDate": "2025-02-24T18:21:55.000Z",
    "Status": "✅ Up-to-date",
    "LatestBuild": 17459173,
    "Rating": 90,
    "RatingPercent": 97.9165885208743,
    "ReviewsTotal": 186617,
    "ReviewsPositive": 182729,
    "ReviewsNegative": 3888,
    "ReviewSummary": "Overwhelmingly Positive"
  },
  "2442460": {
    "Name": "Citizen.Sleeper.2.Starward.Vector",
    "AppID": 2442460,
    "InstalledBuild": 21164079,
    "LatestDate": "2025-12-12T13:52:21.000Z",
    "RatingPercent": 92.54571026722925,
    "ReviewsTotal": 2133,
    "ReviewsPositive": 1974,
    "ReviewsNegative": 159,
    "ReviewSummary": "Very Positive",
    "LatestBuild": 21164079
  },
  "2444750": {
    "Name": "Shape.of.Dreams",
    "AppID": 2444750,
    "InstalledBuild": 21205645,
    "LatestDate": "2026-03-17T02:03:29.000Z",
    "LatestBuild": 22291018,
    "Rating": 89,
    "RatingPercent": 89.87299278240923,
    "ReviewsTotal": 17873,
    "ReviewsPositive": 16063,
    "ReviewsNegative": 1810,
    "ReviewSummary": "Very Positive"
  },
  "2592160": {
    "Name": "Dispatch",
    "AppID": 2592160,
    "InstalledBuild": 22419966,
    "LatestDate": "2026-03-19T20:43:29.000Z",
    "Rating": 87,
    "RatingPercent": 97.71065297464894,
    "ReviewsTotal": 166423,
    "ReviewsPositive": 162613,
    "ReviewsNegative": 3810,
    "ReviewSummary": "Overwhelmingly Positive",
    "LatestBuild": 22419966
  },
  "2680550": {
    "Name": "Hollywood.Animal",
    "AppID": 2680550,
    "InstalledBuild": 22431599,
    "LatestDate": "2026-03-20T11:41:44.000Z",
    "LatestBuild": 22431599,
    "Rating": 73,
    "RatingPercent": 73.79733879222108,
    "ReviewsTotal": 3908,
    "ReviewsPositive": 2884,
    "ReviewsNegative": 1024,
    "ReviewSummary": "Mostly Positive"
  },
  "2742830": {
    "Name": "Monster.Train.2",
    "AppID": 2742830,
    "InstalledBuild": 21910888,
    "LatestDate": "2026-03-19T17:59:47.000Z",
    "LatestBuild": 22420164,
    "Rating": 87,
    "RatingPercent": 95.55022357945249,
    "ReviewsTotal": 9169,
    "ReviewsPositive": 8761,
    "ReviewsNegative": 408,
    "ReviewSummary": "Overwhelmingly Positive"
  },
  "2756920": {
    "Name": "Keep.Driving",
    "AppID": 2756920,
    "InstalledBuild": 21425122,
    "LatestDate": "2026-01-08T19:43:34.000Z",
    "Status": "✅ Up-to-date",
    "LatestBuild": 21425122,
    "Rating": 94,
    "RatingPercent": 94.26272520552737,
    "ReviewsTotal": 5717,
    "ReviewsPositive": 5389,
    "ReviewsNegative": 328,
    "ReviewSummary": "Very Positive"
  },
  "2868840": {
    "Name": "Slay.the.Spire.2",
    "AppID": 2868840,
    "InstalledBuild": 22238966,
    "LatestDate": "2026-03-17T20:47:42.000Z",
    "LatestBuild": 22340209,
    "RatingPercent": 76.92051046792893,
    "ReviewsTotal": 83923,
    "ReviewsPositive": 64554,
    "ReviewsNegative": 19369,
    "ReviewSummary": "Mostly Positive"
  },
  "2922410": {
    "Name": "Achilles.Survivor",
    "AppID": 2922410,
    "InstalledBuild": 21901081,
    "LatestDate": "2026-02-18T15:16:18.000Z",
    "LatestBuild": 21901081,
    "Rating": 82,
    "RatingPercent": 83.27452364149612,
    "ReviewsTotal": 1417,
    "ReviewsPositive": 1180,
    "ReviewsNegative": 237,
    "ReviewSummary": "Very Positive"
  },
  "2996040": {
    "Name": "Teenage.Mutant.Ninja.Turtles.Splintered.Fate",
    "AppID": 2996040,
    "InstalledBuild": 21077936,
    "LatestDate": "2026-03-17T19:47:39.000Z",
    "Status": "✅ Up-to-date",
    "LatestBuild": 22385771,
    "Rating": 82,
    "RatingPercent": 82.91984732824427,
    "ReviewsTotal": 3144,
    "ReviewsPositive": 2607,
    "ReviewsNegative": 537,
    "ReviewSummary": "Very Positive"
  },
  "3167020": {
    "Name": "Escape.From.Duckov",
    "AppID": 3167020,
    "InstalledBuild": 21913702,
    "LatestDate": "2026-02-13T06:38:09.000Z",
    "LatestBuild": 21913702,
    "Rating": 84,
    "RatingPercent": 84.42002828406697,
    "ReviewsTotal": 101117,
    "ReviewsPositive": 85363,
    "ReviewsNegative": 15754,
    "ReviewSummary": "Very Positive"
  },
  "3405340": {
    "Name": "Megabonk",
    "AppID": 3405340,
    "InstalledBuild": 21750826,
    "LatestDate": "2026-02-04T16:05:58.000Z",
    "Rating": 95,
    "RatingPercent": 94.80101265822785,
    "ReviewsTotal": 98750,
    "ReviewsPositive": 93616,
    "ReviewsNegative": 5134,
    "ReviewSummary": "Very Positive",
    "LatestBuild": 21750826
  },
  "3467710": {
    "Name": "Wall.World.2",
    "AppID": 3467710,
    "InstalledBuild": 20888272,
    "LatestDate": "2025-11-21T10:59:42.000Z",
    "LatestBuild": 20888272,
    "Rating": 77,
    "RatingPercent": 76.21722846441948,
    "ReviewsTotal": 1602,
    "ReviewsPositive": 1221,
    "ReviewsNegative": 381,
    "ReviewSummary": "Mostly Positive"
  },
  "3483740": {
    "Name": "Cast.n.Chill",
    "AppID": 3483740,
    "InstalledBuild": 22258338,
    "LatestDate": "2026-03-09T10:11:29.000Z",
    "Rating": 95,
    "RatingPercent": 95.26127415891196,
    "ReviewsTotal": 6985,
    "ReviewsPositive": 6654,
    "ReviewsNegative": 331,
    "ReviewSummary": "Overwhelmingly Positive",
    "LatestBuild": 22258338
  },
  "3631290": {
    "Name": "Slots.and.Daggers",
    "AppID": 3631290,
    "InstalledBuild": 20648272,
    "LatestDate": "2025-11-03T11:49:07.000Z",
    "Rating": 94,
    "RatingPercent": 94.62855347887546,
    "ReviewsTotal": 6367,
    "ReviewsPositive": 6025,
    "ReviewsNegative": 342,
    "ReviewSummary": "Very Positive",
    "LatestBuild": 20648272
  },
  "4035270": {
    "Name": "Space.Rock.Breaker",
    "AppID": 4035270,
    "InstalledBuild": 21809434,
    "LatestDate": "2026-02-06T02:56:57.000Z",
    "RatingPercent": 96.85264663805437,
    "ReviewsTotal": 2796,
    "ReviewsPositive": 2708,
    "ReviewsNegative": 88,
    "ReviewSummary": "Overwhelmingly Positive",
    "LatestBuild": 21809434
  },
  "4038320": {
    "Name": "This.Aint.Even.Poker.Ya.Joker",
    "AppID": 4038320,
    "InstalledBuild": 21177577,
    "LatestDate": "2025-12-15T06:14:28.000Z",
    "LatestBuild": 21177577,
    "Rating": 89,
    "RatingPercent": 87.94701986754967,
    "ReviewsTotal": 1510,
    "ReviewsPositive": 1328,
    "ReviewsNegative": 182,
    "ReviewSummary": "Very Positive"
  }
}