{
  "257850": {
    "Name": "Hyper.Light.Drifter",
    "AppID": 257850,
    "InstalledBuild": 10930509,
    "LatestDate": "2023-04-04T19:48:08.000Z",
    "Rating": 84,
    "RatingPercent": 92.94526876460677,
    "ReviewsTotal": 18399,
    "ReviewsPositive": 17101,
    "ReviewsNegative": 1298,
    "ReviewSummary": "Very Positive",
    "LatestBuild": 10930509
  },
  "268910": {
    "Name": "Cuphead",
    "AppID": 268910,
    "InstalledBuild": 20241530,
    "LatestDate": "2025-10-03T22:10:37.000Z",
    "Rating": 88,
    "RatingPercent": 96.23812303481294,
    "ReviewsTotal": 203861,
    "ReviewsPositive": 196192,
    "ReviewsNegative": 7669,
    "ReviewSummary": "Overwhelmingly Positive",
    "LatestBuild": 20241530
  },
  "323190": {
    "Name": "Frostpunk",
    "AppID": 323190,
    "InstalledBuild": 20303936,
    "LatestDate": "2025-10-20T09:42:34.000Z",
    "RatingPercent": 92.70425724293561,
    "ReviewsTotal": 131611,
    "ReviewsPositive": 122009,
    "ReviewsNegative": 9602,
    "ReviewSummary": "Very Positive",
    "LatestBuild": 20303936
  },
  "330020": {
    "Name": "Children.of.Morta",
    "AppID": 330020,
    "InstalledBuild": 8334433,
    "LatestDate": "2022-03-08T16:02:23.000Z",
    "Rating": 82,
    "RatingPercent": 88.52825464949929,
    "ReviewsTotal": 22368,
    "ReviewsPositive": 19802,
    "ReviewsNegative": 2566,
    "ReviewSummary": "Very Positive",
    "LatestBuild": 8334433
  },
  "367520": {
    "Name": "Hollow.Knight",
    "AppID": 367520,
    "InstalledBuild": 20231655,
    "LatestDate": "2026-02-05T23:18:23.000Z",
    "Status": "✅ Up-to-date",
    "Rating": 87,
    "RatingPercent": 96.91063862129245,
    "ReviewsTotal": 526290,
    "ReviewsPositive": 510031,
    "ReviewsNegative": 16259,
    "ReviewSummary": "Overwhelmingly Positive",
    "LatestBuild": 21656419
  },
  "368340": {
    "Name": "CrossCode",
    "AppID": 368340,
    "InstalledBuild": 20004663,
    "LatestDate": "2025-09-20T13:15:00.000Z",
    "Rating": 86,
    "RatingPercent": 92.86283437677861,
    "ReviewsTotal": 17570,
    "ReviewsPositive": 16316,
    "ReviewsNegative": 1254,
    "ReviewSummary": "Very Positive",
    "LatestBuild": 20004663
  },
  "394310": {
    "Name": "Punch.Club",
    "AppID": 394310,
    "InstalledBuild": 11412837,
    "LatestDate": "2024-01-26T08:51:08.000Z",
    "Rating": 73,
    "RatingPercent": 80.55736001039367,
    "ReviewsTotal": 15394,
    "ReviewsPositive": 12401,
    "ReviewsNegative": 2993,
    "ReviewSummary": "Very Positive",
    "LatestBuild": 1734185
  },
  "503560": {
    "Name": "911.Operator",
    "AppID": 503560,
    "InstalledBuild": 7533741,
    "LatestDate": "2021-10-14T15:35:34.000Z",
    "Rating": 68,
    "RatingPercent": 88.62027374272378,
    "ReviewsTotal": 19069,
    "ReviewsPositive": 16899,
    "ReviewsNegative": 2170,
    "ReviewSummary": "Very Positive",
    "LatestBuild": 7533741
  },
  "504230": {
    "Name": "Celeste",
    "AppID": 504230,
    "InstalledBuild": 17282758,
    "LatestDate": "2025-02-07T17:00:06.000Z",
    "Rating": 88,
    "RatingPercent": 97.42324440625941,
    "ReviewsTotal": 136179,
    "ReviewsPositive": 132670,
    "ReviewsNegative": 3509,
    "ReviewSummary": "Overwhelmingly Positive",
    "LatestBuild": 17282758
  },
  "553420": {
    "Name": "Tunic",
    "AppID": 553420,
    "InstalledBuild": 10650562,
    "LatestDate": "2023-03-02T20:14:47.000Z",
    "Status": "✅ Up-to-date",
    "Rating": 85,
    "RatingPercent": 91.50114928979785,
    "ReviewsTotal": 16967,
    "ReviewsPositive": 15525,
    "ReviewsNegative": 1442,
    "ReviewSummary": "Very Positive",
    "LatestBuild": 10650562
  },
  "588650": {
    "Name": "Dead.Cells",
    "AppID": 588650,
    "InstalledBuild": 15492902,
    "LatestDate": "2024-08-27T08:14:59.000Z",
    "Status": "✅ Up-to-date",
    "Rating": 89,
    "RatingPercent": 97.05409657645872,
    "ReviewsTotal": 177331,
    "ReviewsPositive": 172107,
    "ReviewsNegative": 5224,
    "ReviewSummary": "Overwhelmingly Positive",
    "LatestBuild": 15492902
  },
  "632470": {
    "Name": "Disco.Elysium",
    "AppID": 632470,
    "InstalledBuild": 21464562,
    "LatestDate": "2026-01-23T14:24:58.000Z",
    "Rating": 97,
    "RatingPercent": 92.75025130516553,
    "ReviewsTotal": 123356,
    "ReviewsPositive": 114413,
    "ReviewsNegative": 8943,
    "ReviewSummary": "Very Positive",
    "LatestBuild": 21464562
  },
  "653530": {
    "Name": "Return.of.the.Obra.Dinn",
    "AppID": 653530,
    "InstalledBuild": 9550393,
    "LatestDate": "2022-09-20T07:24:13.000Z",
    "Rating": 89,
    "RatingPercent": 96.759399866367,
    "ReviewsTotal": 32926,
    "ReviewsPositive": 31859,
    "ReviewsNegative": 1067,
    "ReviewSummary": "Overwhelmingly Positive",
    "LatestBuild": 9550393
  },
  "690830": {
    "Name": "Foundation",
    "AppID": 690830,
    "InstalledBuild": 21621209,
    "LatestDate": "2026-01-23T16:53:32.000Z",
    "Rating": 84,
    "RatingPercent": 86.32235851086722,
    "ReviewsTotal": 23235,
    "ReviewsPositive": 20057,
    "ReviewsNegative": 3178,
    "ReviewSummary": "Very Positive",
    "LatestBuild": 21621209
  },
  "692850": {
    "Name": "Bloodstained.Ritual.of.the.Night",
    "AppID": 692850,
    "InstalledBuild": 20844919,
    "LatestDate": "2025-12-23T15:37:31.000Z",
    "Rating": 93,
    "RatingPercent": 93.3809980098769,
    "ReviewsTotal": 40701,
    "ReviewsPositive": 38007,
    "ReviewsNegative": 2694,
    "ReviewSummary": "Very Positive",
    "LatestBuild": 20844919
  },
  "774181": {
    "Name": "Rhythm.Doctor",
    "AppID": 774181,
    "InstalledBuild": 21254178,
    "LatestDate": "2026-01-14T04:25:49.000Z",
    "Rating": 87,
    "RatingPercent": 98.27334726219104,
    "ReviewsTotal": 25367,
    "ReviewsPositive": 24929,
    "ReviewsNegative": 438,
    "ReviewSummary": "Overwhelmingly Positive",
    "LatestBuild": 21487210
  },
  "774361": {
    "Name": "Blasphemous",
    "AppID": 774361,
    "InstalledBuild": 20206233,
    "LatestDate": "2025-10-03T09:46:58.000Z",
    "Status": "✅ Up-to-date",
    "Rating": 77,
    "LatestBuild": 20206233,
    "RatingPercent": 89.80718063265776,
    "ReviewsTotal": 60886,
    "ReviewsPositive": 54680,
    "ReviewsNegative": 6206,
    "ReviewSummary": "Very Positive"
  },
  "867210": {
    "Name": "Songs.of.Conquest",
    "AppID": 867210,
    "InstalledBuild": 21104187,
    "LatestDate": "2026-01-27T14:44:06.000Z",
    "Rating": 85,
    "LatestBuild": 21656629,
    "RatingPercent": 85.85218935825161,
    "ReviewsTotal": 12949,
    "ReviewsPositive": 11117,
    "ReviewsNegative": 1832,
    "ReviewSummary": "Very Positive"
  },
  "894020": {
    "Name": "Deaths.Door",
    "AppID": 894020,
    "InstalledBuild": 7480208,
    "LatestDate": "2021-10-05T10:21:41.000Z",
    "Rating": 85,
    "LatestBuild": 7480208,
    "RatingPercent": 93.26719321903295,
    "ReviewsTotal": 20764,
    "ReviewsPositive": 19366,
    "ReviewsNegative": 1398,
    "ReviewSummary": "Very Positive"
  },
  "921570": {
    "Name": "Octopath.Traveler",
    "AppID": 921570,
    "InstalledBuild": 5272616,
    "LatestDate": "2020-07-22T16:55:34.000Z",
    "Rating": 80,
    "LatestBuild": 5272616,
    "RatingPercent": 85.81547179108155,
    "ReviewsTotal": 16236,
    "ReviewsPositive": 13933,
    "ReviewsNegative": 2303,
    "ReviewSummary": "Very Positive"
  },
  "1030300": {
    "Name": "Hollow.Knight.Silksong",
    "AppID": 1030300,
    "InstalledBuild": 20764176,
    "LatestDate": "2025-11-12T08:42:46.000Z",
    "Status": "✅ Up-to-date",
    "Rating": 90,
    "LatestBuild": 20764176,
    "RatingPercent": 88.94613284339994,
    "ReviewsTotal": 391890,
    "ReviewsPositive": 348571,
    "ReviewsNegative": 43319,
    "ReviewSummary": "Very Positive"
  },
  "1161590": {
    "Name": "Punch.Club.2.Fast.Forward",
    "AppID": 1161590,
    "InstalledBuild": 20464979,
    "LatestDate": "2025-10-20T14:12:49.000Z",
    "Status": "✅ Up-to-date",
    "Rating": 82,
    "LatestBuild": 20464979,
    "RatingPercent": 82.55349165295087,
    "ReviewsTotal": 4253,
    "ReviewsPositive": 3511,
    "ReviewsNegative": 742,
    "ReviewSummary": "Very Positive"
  },
  "1229240": {
    "Name": "Chained.Echoes",
    "AppID": 1229240,
    "InstalledBuild": 21147362,
    "LatestDate": "2025-12-11T13:05:54.000Z",
    "Rating": 91,
    "LatestBuild": 21147362,
    "RatingPercent": 89.15378569557244,
    "ReviewsTotal": 7634,
    "ReviewsPositive": 6806,
    "ReviewsNegative": 828,
    "ReviewSummary": "Very Positive"
  },
  "1244090": {
    "Name": "Sea.of.Stars",
    "AppID": 1244090,
    "InstalledBuild": 20404391,
    "LatestDate": "2025-10-15T14:56:31.000Z",
    "Rating": 87,
    "LatestBuild": 20404391,
    "RatingPercent": 89.14629826425788,
    "ReviewsTotal": 14115,
    "ReviewsPositive": 12583,
    "ReviewsNegative": 1532,
    "ReviewSummary": "Very Positive"
  },
  "1262350": {
    "Name": "Signalis",
    "AppID": 1262350,
    "InstalledBuild": 15862770,
    "LatestDate": "2025-10-05T20:23:08.000Z",
    "Rating": 96,
    "LatestBuild": 20243420,
    "RatingPercent": 96.6848699004176,
    "ReviewsTotal": 31130,
    "ReviewsPositive": 30098,
    "ReviewsNegative": 1032,
    "ReviewSummary": "Overwhelmingly Positive"
  },
  "1264280": {
    "Name": "Slipways",
    "AppID": 1264280,
    "InstalledBuild": 15946357,
    "LatestDate": "2024-10-07T12:28:20.000Z",
    "Rating": 92,
    "LatestBuild": 15946357,
    "RatingPercent": 92.86347517730496,
    "ReviewsTotal": 2256,
    "ReviewsPositive": 2095,
    "ReviewsNegative": 161,
    "ReviewSummary": "Very Positive"
  },
  "1277400": {
    "Name": "Monster.Hunter.Stories.2.Wings.of.Ruin",
    "AppID": 1277400,
    "InstalledBuild": 20139678,
    "LatestDate": "2025-11-26T00:59:37.000Z",
    "Rating": 82,
    "LatestBuild": 20139678,
    "RatingPercent": 82.5201297920923,
    "ReviewsTotal": 16642,
    "ReviewsPositive": 13733,
    "ReviewsNegative": 2909,
    "ReviewSummary": "Very Positive"
  },
  "1280930": {
    "Name": "Astral.Ascent",
    "AppID": 1280930,
    "InstalledBuild": 21587176,
    "LatestDate": "2026-01-21T20:06:19.000Z",
    "Rating": 86,
    "LatestBuild": 21587176,
    "RatingPercent": 94.76202467892219,
    "ReviewsTotal": 7942,
    "ReviewsPositive": 7526,
    "ReviewsNegative": 416,
    "ReviewSummary": "Very Positive"
  },
  "1313140": {
    "Name": "Cult.of.the.Lamb",
    "AppID": 1313140,
    "InstalledBuild": 21791439,
    "LatestDate": "2026-02-10T06:13:03.000Z",
    "RatingPercent": 95.78783151326053,
    "ReviewsTotal": 118585,
    "ReviewsPositive": 113590,
    "ReviewsNegative": 4995,
    "ReviewSummary": "Overwhelmingly Positive",
    "LatestBuild": 21845640
  },
  "1336490": {
    "Name": "Against.the.Storm",
    "AppID": 1336490,
    "InstalledBuild": 21522665,
    "LatestDate": "2026-01-19T12:08:28.000Z",
    "Rating": 91,
    "RatingPercent": 94.7500499044686,
    "ReviewsTotal": 35067,
    "ReviewsPositive": 33226,
    "ReviewsNegative": 1841,
    "ReviewSummary": "Very Positive",
    "LatestBuild": 21522665
  },
  "1361510": {
    "Name": "TMNT.Shredders.Revenge",
    "AppID": 1361510,
    "InstalledBuild": 15664053,
    "LatestDate": "2026-02-14T18:34:36.574Z",
    "Status": "✅ Up-to-date",
    "Rating": 84,
    "RatingPercent": 94.45182956692088,
    "ReviewsTotal": 14293,
    "ReviewsPositive": 13500,
    "ReviewsNegative": 793,
    "ReviewSummary": "Very Positive"
  },
  "1363080": {
    "Name": "Manor.Lords",
    "AppID": 1363080,
    "InstalledBuild": 21209292,
    "LatestDate": "2025-12-19T13:59:22.000Z",
    "Rating": 84,
    "RatingPercent": 84.73314472043732,
    "ReviewsTotal": 83416,
    "ReviewsPositive": 70681,
    "ReviewsNegative": 12735,
    "ReviewSummary": "Very Positive",
    "LatestBuild": 21209292
  },
  "1369630": {
    "Name": "ENDER.LILIES.Quietus.of.the.Knights",
    "AppID": 1369630,
    "InstalledBuild": 8834157,
    "LatestDate": "2022-06-03T07:45:21.000Z",
    "Rating": 86,
    "RatingPercent": 93.87330776694543,
    "ReviewsTotal": 43286,
    "ReviewsPositive": 40634,
    "ReviewsNegative": 2652,
    "ReviewSummary": "Very Positive",
    "LatestBuild": 8834157
  },
  "1458140": {
    "Name": "Pacific.Drive",
    "AppID": 1458140,
    "InstalledBuild": 21140881,
    "LatestDate": "2025-12-16T16:58:15.000Z",
    "Rating": 83,
    "RatingPercent": 83.34221639129187,
    "ReviewsTotal": 24391,
    "ReviewsPositive": 20328,
    "ReviewsNegative": 4063,
    "ReviewSummary": "Very Positive",
    "LatestBuild": 21140881
  },
  "1578650": {
    "Name": "Citizen.Sleeper",
    "AppID": 1578650,
    "InstalledBuild": 21238792,
    "LatestDate": "2025-12-18T10:36:25.000Z",
    "RatingPercent": 92.73602679505966,
    "ReviewsTotal": 9554,
    "ReviewsPositive": 8860,
    "ReviewsNegative": 694,
    "ReviewSummary": "Very Positive",
    "LatestBuild": 21238792
  },
  "1588550": {
    "Name": "Cairn",
    "AppID": 1588550,
    "InstalledBuild": 21769539,
    "LatestDate": "2026-02-04T14:00:24.000Z",
    "RatingPercent": 94.29405520169851,
    "ReviewsTotal": 11304,
    "ReviewsPositive": 10659,
    "ReviewsNegative": 645,
    "ReviewSummary": "Very Positive",
    "LatestBuild": 21769539
  },
  "1593030": {
    "Name": "Terra.Nil",
    "AppID": 1593030,
    "InstalledBuild": 19755773,
    "LatestDate": "2025-08-27T14:17:14.000Z",
    "Status": "✅ Up-to-date",
    "Rating": 79,
    "RatingPercent": 87.5,
    "ReviewsTotal": 8232,
    "ReviewsPositive": 7203,
    "ReviewsNegative": 1029,
    "ReviewSummary": "Very Positive",
    "LatestBuild": 19755773
  },
  "1601580": {
    "Name": "Frostpunk.2",
    "AppID": 1601580,
    "InstalledBuild": 21258134,
    "LatestDate": "2025-12-19T15:19:57.000Z",
    "RatingPercent": 75.02613170378709,
    "ReviewsTotal": 24874,
    "ReviewsPositive": 18662,
    "ReviewsNegative": 6212,
    "ReviewSummary": "Mostly Positive",
    "LatestBuild": 21258134
  },
  "1621690": {
    "Name": "Core.Keeper",
    "AppID": 1621690,
    "InstalledBuild": 21036902,
    "LatestDate": "2025-12-05T10:05:20.000Z",
    "Rating": 85,
    "RatingPercent": 92.9412720331411,
    "ReviewsTotal": 61555,
    "ReviewsPositive": 57210,
    "ReviewsNegative": 4345,
    "ReviewSummary": "Very Positive",
    "LatestBuild": 21036902
  },
  "1637320": {
    "Name": "Dome.Keeper",
    "AppID": 1637320,
    "InstalledBuild": 17779621,
    "LatestDate": "2025-03-19T15:38:50.000Z",
    "Rating": 92,
    "RatingPercent": 92.28004291845494,
    "ReviewsTotal": 18640,
    "ReviewsPositive": 17201,
    "ReviewsNegative": 1439,
    "ReviewSummary": "Very Positive",
    "LatestBuild": 17779621
  },
  "1649950": {
    "Name": "News.Tower",
    "AppID": 1649950,
    "InstalledBuild": 21396289,
    "LatestDate": "2026-01-08T09:24:29.000Z",
    "Rating": 94,
    "RatingPercent": 94.6353522867738,
    "ReviewsTotal": 4045,
    "ReviewsPositive": 3828,
    "ReviewsNegative": 217,
    "ReviewSummary": "Very Positive",
    "LatestBuild": 21420922
  },
  "1718570": {
    "Name": "ASTLIBRA.Revision",
    "AppID": 1718570,
    "InstalledBuild": 16656423,
    "LatestDate": "2026-02-10T15:05:36.000Z",
    "Rating": 95,
    "RatingPercent": 95.29886969213537,
    "ReviewsTotal": 29461,
    "ReviewsPositive": 28076,
    "ReviewsNegative": 1385,
    "ReviewSummary": "Overwhelmingly Positive",
    "LatestBuild": 21868037
  },
  "1755830": {
    "Name": "Astrea.Six.Sided.Oracles",
    "AppID": 1755830,
    "InstalledBuild": 18016665,
    "LatestDate": "2025-04-08T00:59:56.000Z",
    "Rating": 85,
    "RatingPercent": 91.68943533697632,
    "ReviewsTotal": 4392,
    "ReviewsPositive": 4027,
    "ReviewsNegative": 365,
    "ReviewSummary": "Very Positive",
    "LatestBuild": 18016665
  },
  "1782460": {
    "Name": "Hell.Clock",
    "AppID": 1782460,
    "InstalledBuild": 20968706,
    "LatestDate": "2025-11-27T16:57:03.000Z",
    "Rating": 84,
    "RatingPercent": 83.85447985568251,
    "ReviewsTotal": 3326,
    "ReviewsPositive": 2789,
    "ReviewsNegative": 537,
    "ReviewSummary": "Very Positive",
    "LatestBuild": 20968706
  },
  "1868140": {
    "Name": "DAVE.THE.DIVER",
    "AppID": 1868140,
    "InstalledBuild": 21569228,
    "LatestDate": "2026-01-21T01:44:10.000Z",
    "Status": "✅ Up-to-date",
    "Rating": 90,
    "RatingPercent": 96.81453386103782,
    "ReviewsTotal": 145536,
    "ReviewsPositive": 140900,
    "ReviewsNegative": 4636,
    "ReviewSummary": "Overwhelmingly Positive",
    "LatestBuild": 21569228
  },
  "1904480": {
    "Name": "Absolum",
    "AppID": 1904480,
    "InstalledBuild": 20526751,
    "LatestDate": "2026-02-12T16:00:46.000Z",
    "Rating": 87,
    "RatingPercent": 93.27075460197489,
    "ReviewsTotal": 8203,
    "ReviewsPositive": 7651,
    "ReviewsNegative": 552,
    "ReviewSummary": "Very Positive",
    "LatestBuild": 21713036
  },
  "1940340": {
    "Name": "Darkest.Dungeon.II",
    "AppID": 1940340,
    "InstalledBuild": 20612299,
    "LatestDate": "2025-10-30T21:27:33.000Z",
    "Rating": 81,
    "RatingPercent": 75.28705531606302,
    "ReviewsTotal": 24821,
    "ReviewsPositive": 18687,
    "ReviewsNegative": 6134,
    "ReviewSummary": "Mostly Positive",
    "LatestBuild": 20612299
  },
  "1942280": {
    "Name": "Brotato",
    "AppID": 1942280,
    "InstalledBuild": 20675512,
    "LatestDate": "2026-02-12T14:17:24.000Z",
    "Status": "✅ Up-to-date",
    "Rating": 96,
    "RatingPercent": 96.60098522167488,
    "ReviewsTotal": 109620,
    "ReviewsPositive": 105894,
    "ReviewsNegative": 3726,
    "ReviewSummary": "Overwhelmingly Positive",
    "LatestBuild": 21901768
  },
  "1970580": {
    "Name": "Backpack.Hero",
    "AppID": 1970580,
    "InstalledBuild": 15631088,
    "LatestDate": "2024-09-08T17:06:09.000Z",
    "Rating": 76,
    "RatingPercent": 87.00965416106563,
    "ReviewsTotal": 8183,
    "ReviewsPositive": 7120,
    "ReviewsNegative": 1063,
    "ReviewSummary": "Very Positive",
    "LatestBuild": 15631088
  },
  "1971650": {
    "Name": "OCTOPATH.TRAVELER.II",
    "AppID": 1971650,
    "InstalledBuild": 13399590,
    "LatestDate": "2024-06-05T15:54:48.000Z",
    "Rating": 94,
    "RatingPercent": 94.19235433020614,
    "ReviewsTotal": 15669,
    "ReviewsPositive": 14759,
    "ReviewsNegative": 910,
    "ReviewSummary": "Very Positive",
    "LatestBuild": 13399590
  },
  "2062430": {
    "Name": "BALL.x.PIT",
    "AppID": 2062430,
    "InstalledBuild": 21684508,
    "LatestDate": "2026-01-28T15:13:31.000Z",
    "Rating": 95,
    "RatingPercent": 95.60867640548916,
    "ReviewsTotal": 22590,
    "ReviewsPositive": 21598,
    "ReviewsNegative": 992,
    "ReviewSummary": "Overwhelmingly Positive",
    "LatestBuild": 21684508
  },
  "2066020": {
    "Name": "Soulstone.Survivors",
    "AppID": 2066020,
    "InstalledBuild": 21223726,
    "LatestDate": "2025-12-18T21:05:25.000Z",
    "Status": "⚠️ Update available",
    "Rating": 91,
    "RatingPercent": 91.42084942084942,
    "ReviewsTotal": 25900,
    "ReviewsPositive": 23678,
    "ReviewsNegative": 2222,
    "ReviewSummary": "Very Positive",
    "LatestBuild": 21223726
  },
  "2103140": {
    "Name": "Magicraft",
    "AppID": 2103140,
    "InstalledBuild": 21745630,
    "LatestDate": "2026-02-02T10:11:17.000Z",
    "Rating": 92,
    "RatingPercent": 92.64837268666241,
    "ReviewsTotal": 15670,
    "ReviewsPositive": 14518,
    "ReviewsNegative": 1152,
    "ReviewSummary": "Very Positive",
    "LatestBuild": 21745630
  },
  "2114740": {
    "Name": "Blasphemous.2",
    "AppID": 2114740,
    "InstalledBuild": 20202981,
    "LatestDate": "2025-10-03T12:41:18.000Z",
    "Status": "✅ Up-to-date",
    "Rating": 83,
    "RatingPercent": 90.55889037822718,
    "ReviewsTotal": 17159,
    "ReviewsPositive": 15539,
    "ReviewsNegative": 1620,
    "ReviewSummary": "Very Positive",
    "LatestBuild": 20202981
  },
  "2126190": {
    "Name": "Rue.Valley",
    "AppID": 2126190,
    "InstalledBuild": 21242075,
    "LatestDate": "2026-01-28T14:19:07.000Z",
    "Rating": 64,
    "RatingPercent": 64.27104722792608,
    "ReviewsTotal": 1461,
    "ReviewsPositive": 939,
    "ReviewsNegative": 522,
    "ReviewSummary": "Mixed",
    "LatestBuild": 21669970
  },
  "2179850": {
    "Name": "Cobalt.Core",
    "AppID": 2179850,
    "InstalledBuild": 21547655,
    "LatestDate": "2026-02-10T23:30:08.000Z",
    "Rating": 94,
    "RatingPercent": 96.17472852912142,
    "ReviewsTotal": 4052,
    "ReviewsPositive": 3897,
    "ReviewsNegative": 155,
    "ReviewSummary": "Overwhelmingly Positive",
    "LatestBuild": 21874666
  },
  "2239150": {
    "Name": "Thronefall",
    "AppID": 2239150,
    "InstalledBuild": 17216593,
    "LatestDate": "2025-02-03T11:39:41.000Z",
    "Rating": 96,
    "RatingPercent": 96.4024860499932,
    "ReviewsTotal": 22043,
    "ReviewsPositive": 21250,
    "ReviewsNegative": 793,
    "ReviewSummary": "Overwhelmingly Positive",
    "LatestBuild": 17216593
  },
  "2273430": {
    "Name": "BlazBlue.Entropy.Effect",
    "AppID": 2273430,
    "InstalledBuild": 20777388,
    "LatestDate": "2026-02-13T08:00:38.000Z",
    "RatingPercent": 94.66483468295964,
    "ReviewsTotal": 34207,
    "ReviewsPositive": 32382,
    "ReviewsNegative": 1825,
    "ReviewSummary": "Very Positive",
    "LatestBuild": 21915958
  },
  "2308630": {
    "Name": "Dawnfolk",
    "AppID": 2308630,
    "InstalledBuild": 19969051,
    "LatestDate": "2026-02-13T08:12:38.000Z",
    "RatingPercent": 95.72192513368985,
    "ReviewsTotal": 561,
    "ReviewsPositive": 537,
    "ReviewsNegative": 24,
    "ReviewSummary": "Overwhelmingly Positive",
    "LatestBuild": 21916093
  },
  "2321470": {
    "Name": "Deep.Rock.Galactic.Survivor",
    "AppID": 2321470,
    "InstalledBuild": 21189700,
    "LatestDate": "2025-12-15T14:04:56.000Z",
    "Status": "✅ Up-to-date",
    "Rating": 86,
    "RatingPercent": 86.64215952841884,
    "ReviewsTotal": 45973,
    "ReviewsPositive": 39832,
    "ReviewsNegative": 6141,
    "ReviewSummary": "Very Positive",
    "LatestBuild": 21189700
  },
  "2334730": {
    "Name": "Death.Must.Die",
    "AppID": 2334730,
    "InstalledBuild": 21650210,
    "LatestDate": "2026-01-26T15:49:03.000Z",
    "LatestBuild": 21650210,
    "Rating": 90,
    "RatingPercent": 90.59519894771458,
    "ReviewsTotal": 21287,
    "ReviewsPositive": 19285,
    "ReviewsNegative": 2002,
    "ReviewSummary": "Very Positive"
  },
  "2350790": {
    "Name": "Moonlighter.2.The.Endless.Vault",
    "AppID": 2350790,
    "InstalledBuild": 21465756,
    "LatestDate": "2026-01-21T08:49:24.000Z",
    "LatestBuild": 21465756,
    "Rating": 87,
    "RatingPercent": 86.88524590163934,
    "ReviewsTotal": 2257,
    "ReviewsPositive": 1961,
    "ReviewsNegative": 296,
    "ReviewSummary": "Very Positive"
  },
  "2379780": {
    "Name": "Balatro",
    "AppID": 2379780,
    "InstalledBuild": 17459173,
    "LatestDate": "2025-02-24T18:21:55.000Z",
    "Status": "✅ Up-to-date",
    "LatestBuild": 17459173,
    "Rating": 90,
    "RatingPercent": 97.92870326885901,
    "ReviewsTotal": 183122,
    "ReviewsPositive": 179329,
    "ReviewsNegative": 3793,
    "ReviewSummary": "Overwhelmingly Positive"
  },
  "2442460": {
    "Name": "Citizen.Sleeper.2.Starward.Vector",
    "AppID": 2442460,
    "InstalledBuild": 20765567,
    "LatestDate": "2025-12-12T13:52:21.000Z",
    "LatestBuild": 21164079,
    "RatingPercent": 92.69361909400877,
    "ReviewsTotal": 2053,
    "ReviewsPositive": 1903,
    "ReviewsNegative": 150,
    "ReviewSummary": "Very Positive"
  },
  "2444750": {
    "Name": "Shape.of.Dreams",
    "AppID": 2444750,
    "InstalledBuild": 21205645,
    "LatestDate": "2025-12-17T06:01:05.000Z",
    "LatestBuild": 21205645,
    "Rating": 89,
    "RatingPercent": 89.73828794234065,
    "ReviewsTotal": 16927,
    "ReviewsPositive": 15190,
    "ReviewsNegative": 1737,
    "ReviewSummary": "Very Positive"
  },
  "2592160": {
    "Name": "Dispatch",
    "AppID": 2592160,
    "InstalledBuild": 21723382,
    "LatestDate": "2026-02-11T17:59:28.000Z",
    "LatestBuild": 21822905,
    "Rating": 87,
    "RatingPercent": 97.74761731673208,
    "ReviewsTotal": 162317,
    "ReviewsPositive": 158661,
    "ReviewsNegative": 3656,
    "ReviewSummary": "Overwhelmingly Positive"
  },
  "2680550": {
    "Name": "Hollywood.Animal",
    "AppID": 2680550,
    "InstalledBuild": 21684216,
    "LatestDate": "2026-01-28T15:23:42.000Z",
    "LatestBuild": 21684216,
    "Rating": 73,
    "RatingPercent": 73.66771159874608,
    "ReviewsTotal": 3828,
    "ReviewsPositive": 2820,
    "ReviewsNegative": 1008,
    "ReviewSummary": "Mostly Positive"
  },
  "2742830": {
    "Name": "Monster.Train.2",
    "AppID": 2742830,
    "InstalledBuild": 20804247,
    "LatestDate": "2026-02-12T23:38:03.000Z",
    "LatestBuild": 21910888,
    "Rating": 87,
    "RatingPercent": 95.59620596205963,
    "ReviewsTotal": 8856,
    "ReviewsPositive": 8466,
    "ReviewsNegative": 390,
    "ReviewSummary": "Overwhelmingly Positive"
  },
  "2756920": {
    "Name": "Keep.Driving",
    "AppID": 2756920,
    "InstalledBuild": 21425122,
    "LatestDate": "2026-01-08T19:43:34.000Z",
    "Status": "✅ Up-to-date",
    "LatestBuild": 21425122,
    "Rating": 94,
    "RatingPercent": 94.27797833935017,
    "ReviewsTotal": 5540,
    "ReviewsPositive": 5223,
    "ReviewsNegative": 317,
    "ReviewSummary": "Very Positive"
  },
  "2922410": {
    "Name": "Achilles.Survivor",
    "AppID": 2922410,
    "InstalledBuild": 20679717,
    "LatestDate": "2025-11-20T15:08:57.000Z",
    "LatestBuild": 20679717,
    "Rating": 82,
    "RatingPercent": 83.22246858832226,
    "ReviewsTotal": 1353,
    "ReviewsPositive": 1126,
    "ReviewsNegative": 227,
    "ReviewSummary": "Very Positive"
  },
  "2996040": {
    "Name": "Teenage.Mutant.Ninja.Turtles.Splintered.Fate",
    "AppID": 2996040,
    "InstalledBuild": 21077936,
    "LatestDate": "2025-12-16T16:00:19.000Z",
    "Status": "✅ Up-to-date",
    "LatestBuild": 21077936,
    "Rating": 82,
    "RatingPercent": 82.27401129943502,
    "ReviewsTotal": 2832,
    "ReviewsPositive": 2330,
    "ReviewsNegative": 502,
    "ReviewSummary": "Very Positive"
  },
  "3167020": {
    "Name": "Escape.from.Duckov",
    "AppID": 3167020,
    "InstalledBuild": 21315576,
    "LatestDate": "2026-02-13T06:38:09.000Z",
    "LatestBuild": 21913702,
    "Rating": 84,
    "RatingPercent": 84.36681838321182,
    "ReviewsTotal": 99308,
    "ReviewsPositive": 83783,
    "ReviewsNegative": 15525,
    "ReviewSummary": "Very Positive"
  },
  "3405340": {
    "Name": "Megabonk",
    "AppID": 3405340,
    "InstalledBuild": 21750826,
    "LatestDate": "2026-02-04T16:05:58.000Z",
    "LatestBuild": 21750826,
    "Rating": 95,
    "RatingPercent": 94.89404704852791,
    "ReviewsTotal": 95986,
    "ReviewsPositive": 91085,
    "ReviewsNegative": 4901,
    "ReviewSummary": "Very Positive"
  },
  "3467710": {
    "Name": "Wall.World.2",
    "AppID": 3467710,
    "InstalledBuild": 20888272,
    "LatestDate": "2025-11-21T10:59:42.000Z",
    "LatestBuild": 20888272,
    "Rating": 77,
    "RatingPercent": 76.83799609629148,
    "ReviewsTotal": 1537,
    "ReviewsPositive": 1181,
    "ReviewsNegative": 356,
    "ReviewSummary": "Mostly Positive"
  },
  "3483740": {
    "Name": "Cast.n.Chill",
    "AppID": 3483740,
    "InstalledBuild": 21242034,
    "LatestDate": "2025-12-18T23:09:13.000Z",
    "LatestBuild": 21242034,
    "Rating": 95,
    "RatingPercent": 95.36883391160055,
    "ReviewsTotal": 6629,
    "ReviewsPositive": 6322,
    "ReviewsNegative": 307,
    "ReviewSummary": "Overwhelmingly Positive"
  },
  "3631290": {
    "Name": "Slots.and.Daggers",
    "AppID": 3631290,
    "InstalledBuild": 20648272,
    "LatestDate": "2025-11-03T11:49:07.000Z",
    "LatestBuild": 20648272,
    "Rating": 94,
    "RatingPercent": 94.68416735028711,
    "ReviewsTotal": 6095,
    "ReviewsPositive": 5771,
    "ReviewsNegative": 324,
    "ReviewSummary": "Very Positive"
  },
  "4035270": {
    "Name": "Space.Rock.Breaker",
    "AppID": 4035270,
    "InstalledBuild": 21315276,
    "LatestDate": "2026-02-06T02:56:57.000Z",
    "LatestBuild": 21809434,
    "RatingPercent": 97.17615419094577,
    "ReviewsTotal": 2231,
    "ReviewsPositive": 2168,
    "ReviewsNegative": 63,
    "ReviewSummary": "Overwhelmingly Positive"
  },
  "4038320": {
    "Name": "This.Aint.Even.Poker.Ya.Joker",
    "AppID": 4038320,
    "InstalledBuild": 21177577,
    "LatestDate": "2025-12-15T06:14:28.000Z",
    "LatestBuild": 21177577,
    "Rating": 89,
    "RatingPercent": 88.68205510052121,
    "ReviewsTotal": 1343,
    "ReviewsPositive": 1191,
    "ReviewsNegative": 152,
    "ReviewSummary": "Very Positive"
  }
}